{"comment_id":{"0":"gl6gxu2","1":"glgme3v","2":"gl16qyj","3":"gl17zzs","4":"gkt4zc4","5":"gl35f2m","6":"gl4jb0z","7":"gl57tjr","8":"gl5lo7z","9":"glat8fx","10":"gle3lol","11":"gkphq6s","12":"gkrev31","13":"gkroaii","14":"gkszhh6","15":"gktnh4n","16":"gkur5j4","17":"gkvolgy","18":"gkwmp8n","19":"gkxpw4y","20":"gkz5rjk","21":"gkzlzge","22":"gl0oblf","23":"gl1hh7v","24":"gl1y6j4","25":"gl33q0h","26":"gl3a5x9","27":"gl5uxqu","28":"gl7jfcg","29":"gl9sizt","30":"gla3kh6","31":"glallmw","32":"glc86q3","33":"gldo9vv","34":"glek2vf","35":"glhu1ib","36":"gliqd3v","37":"gliy0si","38":"gkt5yts","39":"gkpgcp6","40":"gkqyc8g","41":"gkqz5m9","42":"gkr1j2w","43":"gkrk0m8","44":"gksewul","45":"gktq9c5","46":"gktz4nv","47":"gkucao5","48":"gkw2edh","49":"gkwembj","50":"gkwsjnz","51":"gkx889u","52":"gkxafr4","53":"gkyn1qd","54":"gkywnux","55":"gkzsd7r","56":"gl011gc","57":"gl14bdo","58":"gl1g5n1","59":"gl67cfo","60":"gl67lsi","61":"gl6ovp0","62":"gl6ycbu","63":"gl78k3x","64":"gl7ifw1","65":"gl7jqgi","66":"gl8ixny","67":"glakm8v","68":"gldkf91","69":"gle4pwf","70":"gleb5di","71":"glfg179","72":"glfs82n","73":"glgc74r","74":"glifotu","75":"glil5pl","76":"glj4au5","77":"glj9tl9","78":"gljge3b","79":"glk9fzl","80":"glkc00k","81":"gkqhifw","82":"gkpj2w9","83":"gkpqnwb","84":"gl6cr6q","85":"glbkxt2","86":"glgah6y","87":"gkq8q7y","88":"gl10jmt","89":"glktn3q","90":"glbnf5k","91":"gl4kceo","92":"glchas1","93":"gl8lfdz"},"comment_parent_id":{"0":"t3_l4ne4b","1":"t3_l4ne4b","2":"t3_l4ne4b","3":"t3_l4ne4b","4":"t3_l4ne4b","5":"t3_l4ne4b","6":"t3_l4ne4b","7":"t3_l4ne4b","8":"t3_l4ne4b","9":"t3_l4ne4b","10":"t3_l4ne4b","11":"t3_l4ne4b","12":"t3_l4ne4b","13":"t3_l4ne4b","14":"t3_l4ne4b","15":"t3_l4ne4b","16":"t3_l4ne4b","17":"t3_l4ne4b","18":"t3_l4ne4b","19":"t3_l4ne4b","20":"t3_l4ne4b","21":"t3_l4ne4b","22":"t3_l4ne4b","23":"t3_l4ne4b","24":"t3_l4ne4b","25":"t3_l4ne4b","26":"t3_l4ne4b","27":"t3_l4ne4b","28":"t3_l4ne4b","29":"t3_l4ne4b","30":"t3_l4ne4b","31":"t3_l4ne4b","32":"t3_l4ne4b","33":"t3_l4ne4b","34":"t3_l4ne4b","35":"t3_l4ne4b","36":"t3_l4ne4b","37":"t3_l4ne4b","38":"t3_l4ne4b","39":"t3_l4ne4b","40":"t3_l4ne4b","41":"t3_l4ne4b","42":"t3_l4ne4b","43":"t3_l4ne4b","44":"t3_l4ne4b","45":"t3_l4ne4b","46":"t3_l4ne4b","47":"t3_l4ne4b","48":"t3_l4ne4b","49":"t3_l4ne4b","50":"t3_l4ne4b","51":"t3_l4ne4b","52":"t3_l4ne4b","53":"t3_l4ne4b","54":"t3_l4ne4b","55":"t3_l4ne4b","56":"t3_l4ne4b","57":"t3_l4ne4b","58":"t3_l4ne4b","59":"t3_l4ne4b","60":"t3_l4ne4b","61":"t3_l4ne4b","62":"t3_l4ne4b","63":"t3_l4ne4b","64":"t3_l4ne4b","65":"t3_l4ne4b","66":"t3_l4ne4b","67":"t3_l4ne4b","68":"t3_l4ne4b","69":"t3_l4ne4b","70":"t3_l4ne4b","71":"t3_l4ne4b","72":"t3_l4ne4b","73":"t3_l4ne4b","74":"t3_l4ne4b","75":"t3_l4ne4b","76":"t3_l4ne4b","77":"t3_l4ne4b","78":"t3_l4ne4b","79":"t3_l4ne4b","80":"t3_l4ne4b","81":"t3_l4ne4b","82":"t3_l4ne4b","83":"t3_l4ne4b","84":"t3_l4ne4b","85":"t3_l4ne4b","86":"t3_l4ne4b","87":"t3_l4ne4b","88":"t3_l4ne4b","89":"t3_l4ne4b","90":"t3_l4ne4b","91":"t3_l4ne4b","92":"t3_l4ne4b","93":"t1_gl6ht33"},"comment_created_utc":{"0":1611885806.0,"1":1612080071.0,"2":1611798227.0,"3":1611798780.0,"4":1611654901.0,"5":1611841836.0,"6":1611857773.0,"7":1611867198.0,"8":1611872192.0,"9":1611959179.0,"10":1612030794.0,"11":1611583785.0,"12":1611614885.0,"13":1611619675.0,"14":1611649411.0,"15":1611669566.0,"16":1611687182.0,"17":1611700986.0,"18":1611717534.0,"19":1611746593.0,"20":1611769534.0,"21":1611775788.0,"22":1611791269.0,"23":1611803043.0,"24":1611811788.0,"25":1611841182.0,"26":1611843484.0,"27":1611876070.0,"28":1611905524.0,"29":1611945841.0,"30":1611949688.0,"31":1611955956.0,"32":1611984509.0,"33":1612023817.0,"34":1612038461.0,"35":1612112314.0,"36":1612127144.0,"37":1612130675.0,"38":1611655877.0,"39":1611582995.0,"40":1611607162.0,"41":1611607529.0,"42":1611608597.0,"43":1611617450.0,"44":1611633819.0,"45":1611671072.0,"46":1611675266.0,"47":1611681067.0,"48":1611707434.0,"49":1611713480.0,"50":1611720655.0,"51":1611731116.0,"52":1611732941.0,"53":1611763295.0,"54":1611766571.0,"55":1611778487.0,"56":1611781806.0,"57":1611797164.0,"58":1611802440.0,"59":1611881473.0,"60":1611881589.0,"61":1611889439.0,"62":1611893711.0,"63":1611898822.0,"64":1611904855.0,"65":1611905736.0,"66":1611929465.0,"67":1611955575.0,"68":1612021941.0,"69":1612031306.0,"70":1612034249.0,"71":1612054356.0,"72":1612060785.0,"73":1612072158.0,"74":1612122180.0,"75":1612124708.0,"76":1612133626.0,"77":1612136294.0,"78":1612139432.0,"79":1612153747.0,"80":1612155254.0,"81":1611599721.0,"82":1611584516.0,"83":1611588219.0,"84":1611883916.0,"85":1611972247.0,"86":1612071030.0,"87":1611595925.0,"88":1611795623.0,"89":1612168076.0,"90":1611973484.0,"91":1611858385.0,"92":1611991047.0,"93":1611930488.0},"comment_body":{"0":"<div class=\"md\"><p>What should I buy with 4 shares of $GME if it hits the moon at $40k per share? I got $20k left in student loans. I\u2019d throw a Wrangler at my mom, so 911 Carrera is out of the question.<\/p>\n<\/div>","1":"<div class=\"md\"><p>Location: Texas<\/p>\n\n<p>Price range: $20-30k, can stretch a bit further<\/p>\n\n<p>Lease or Buy: buy<\/p>\n\n<p>New or used: new<\/p>\n\n<p>Type of vehicle: preferably hatchback, sedan maybe<\/p>\n\n<p>Must haves: reasonably efficient, good power (around 6 second 0-60), no CVT or trash DCT, shift lever (no button or rotary dial shifter)<\/p>\n\n<p>Desired transmission (auto\/manual, etc):Auto<\/p>\n\n<p>Intended use: daily driver, occasional spirited driving <\/p>\n\n<p>Vehicles you&#39;ve already considered: Mazda 3 turbo, Jetta GLI, Kia K5 GT, dodge challenger<\/p>\n\n<p>Is this your 1st vehicle: no<\/p>\n\n<p>Do you need a Warranty: yes<\/p>\n\n<p>Can you do Minor work on your own vehicle: only extremely minor work (air filters, wiper blades, etc)<\/p>\n\n<p>Can you do Major work on your own vehicle: no<\/p>\n\n<p>Additional Notes:<\/p>\n\n<p>I&#39;ve been driving stick forever but my knees\/ankles aren&#39;t what they used to be something the clutch is unpleasant to operate, traffic has also gotten monstrously bad over here in recent years so I&#39;m looking to get an automatic car that isn&#39;t a snoozefest.<\/p>\n\n<p>Dodge challenger seems like an oddball in my already considered list, but a v6 challenger is hard to beat in terms of power, out the door price, and cool looks. I also appreciate how simple it is relative to a lot of the other cars. No DCT, no direct injection, etc. <\/p>\n\n<p>The GTI is a natural recommendation, but the GLI seems a better value and I think it looks a bit less bland.<\/p>\n\n<p>The Kia doesn&#39;t appear to exist on dealer lots yet. I don&#39;t care for the sonata n-line counterpart.<\/p>\n\n<p>The Mazda 3 is extremely nice, but I&#39;m interested in the top trim and it&#39;s really stretching my budget.<\/p>\n<\/div>","2":"<div class=\"md\"><p>United States.<\/p>\n\n<p>Should I buy a 2020 Supra GR 3.0 Premium with 3k miles at $48,000 <\/p>\n\n<p>or <\/p>\n\n<p>Should I buy a new 2021 3.0 Supra GR (non premium with no JBL or Nav) for $52,000 - $54,000?<\/p>\n<\/div>","3":"<div class=\"md\"><p>Location: Denver, CO<\/p>\n\n<p>Price range: $5-10k<\/p>\n\n<p>Lease or Buy: Cash purchase<\/p>\n\n<p>New or used: Used<\/p>\n\n<p>Type of vehicle: Convertible<\/p>\n\n<p>Must haves: Character<\/p>\n\n<p>Desired transmission (auto\/manual, etc): Manual only<\/p>\n\n<p>Intended use: Very low mileage (&lt;5k annually), almost exclusively for pleasure. Cruises in the city, some light mountain roads.<\/p>\n\n<p>Vehicles you&#39;ve already considered: Boxster, VW Cabriolet, E30, Miata, Z3.<\/p>\n\n<p>Is this your 1st vehicle: No.<\/p>\n\n<p>Do you need a Warranty: God, no.<\/p>\n\n<p>Can you do Minor work on your own vehicle: Yes, but downtown living offers very little space (secured parking garage).<\/p>\n\n<p>Can you do Major work on your own vehicle: Not on my life.<\/p>\n\n<p>Additional Notes: My long commute has been shortened dramatically (working remotely with seldom local office visits). The 335i M-sport is too much car to sit and collect dust while I dish out payments. RWD is fine, or even preferred. What\u2019s the best older, fun, drop top?<\/p>\n<\/div>","4":"<div class=\"md\"><p>Location : Saudi Arabia \nPrice range : 40000 to 50000 sr\nLease or buy : buy\nType of vehicle : luxury\nMust have : smooth ride safe no turbo and kinda reliable \nTransmission: auto\nIntended use : daily driver\nWhat I have considered: bmw 7 series from 2009 to 2011 \nDo you need warranty: no\nFirst vehicle : yes\nMinor work : yes\nMajor work : kinda<\/p>\n<\/div>","5":"<div class=\"md\"><p>Location: Southeast, USA<\/p>\n\n<p>Price range: $10k or less <\/p>\n\n<p>Lease or Buy: Buy<\/p>\n\n<p>New or used: Either<\/p>\n\n<p>Type of vehicle: Car (looking for first car)<\/p>\n\n<p>Must haves: First car so fuel efficiency and AWD<\/p>\n\n<p>Desired transmission: Either<\/p>\n\n<p>Intended use: Daily car<\/p>\n\n<p>Vehicles you&#39;ve already considered: <\/p>\n\n<p>Is this your 1st vehicle: Yes<\/p>\n\n<p>Do you need a Warranty: No<\/p>\n\n<p>Can you do Minor work on your own vehicle: Trying to learn<\/p>\n\n<p>Can you do Major work on your own vehicle: No<\/p>\n\n<p>Additional Notes: This is my first car. I want something I can learn to work on but also good for daily driving. Also want to try getting into autocrossing.<\/p>\n<\/div>","6":"<div class=\"md\"><p>Location: Montana, USA<\/p>\n\n<p>Price range: 17,500 (preferably less though) <\/p>\n\n<p>Lease or Buy: buy<\/p>\n\n<p>New or used: used<\/p>\n\n<p>Type of vehicle: SUV or Crossover<\/p>\n\n<p>Must haves: 4x4 or AWD, Fuel efficient, can sleep in the back with rear seats removed (I am 6&#39; tall)<\/p>\n\n<p>Desired transmission (auto\/manual, etc): auto <\/p>\n\n<p>Intended use: Daily Driver, minor off-road driving (like to a campsite on a dirt road), snow<\/p>\n\n<p>Vehicles you&#39;ve already considered: CX-5 AWD, RAV4, Subaru Outback (but I think they are ugly) <\/p>\n\n<p>Is this your 1st vehicle: no<\/p>\n\n<p>Do you need a Warranty: preferably<\/p>\n\n<p>Can you do Minor work on your own vehicle: (fluids, alternator, battery, brake pads etc) yes<\/p>\n\n<p>Can you do Major work on your own vehicle: (engine and transmission, timing belt\/chains, body work, suspension etc ) no<\/p>\n\n<p>Additional Notes: preferably something that isn&#39;t pathetically slow and bulky - I am coming from an Acura RSX but need more space and versatility in a less coupe friendly state.<\/p>\n<\/div>","7":"<div class=\"md\"><p>Hello,<\/p>\n\n<p>Looking  to buy a used car which I will likely sell in a year when my other cars  are shipped to me. Want something that is not super expensive (hoping ~  5k plus minus a few thousand), that will hold its value. Something I  can buy today and then sell in a year only loosing a small amount of  value (say 1k).<\/p>\n\n<p>Quite like  small(ish) SUVs (and will to pay a little more), but happy with a  mid-size 2WD car. Is my budget reasonable. What can people reecommend?<\/p>\n\n<p>Will  I HAVE to go private to be able to make this work. Might feel a little  safer buying through dealer (should I feel that way, haha?).<\/p>\n\n<p>Thanks<\/p>\n<\/div>","8":"<div class=\"md\"><p>Location: Ontario Canada<\/p>\n\n<p>Price range: 30-40k CAD (25-30k usd)<\/p>\n\n<p>Lease or Buy: Buy<\/p>\n\n<p>New or used: Used (suggestions for new also appreciated)<\/p>\n\n<p>Type of vehicle: Sedan\/Coupe\/anything but an SUV<\/p>\n\n<p>Must haves: AWD and a good interior (good infotainment with Carplay)<\/p>\n\n<p>Desired transmission (auto\/manual, etc): Auto<\/p>\n\n<p>Intended use: Daily commuter car<\/p>\n\n<p>Vehicles you&#39;ve already considered: 2018 Audi A4\/A5, 2017-2018 BMW 430i\/330i<\/p>\n\n<p>Is this your 1st vehicle: Yes<\/p>\n\n<p>Do you need a Warranty: Would be nice<\/p>\n\n<p>Can you do Minor work on your own vehicle: Yes<\/p>\n\n<p>Can you do Major work on your own vehicle: No<\/p>\n\n<p>Additional Notes: Strongly considering the 2018 A5 with CPO warranty, would like to know about its reliability or if there are better options, thanks<\/p>\n<\/div>","9":"<div class=\"md\"><blockquote>\n<p><strong>Location:<\/strong> Midwest\/indiana  <\/p>\n\n<p><strong>Price range:<\/strong> 10-15k  <\/p>\n\n<p><strong>Lease or Buy:<\/strong> Buy  <\/p>\n\n<p><strong>New or used:<\/strong> used  <\/p>\n\n<p><strong>Type of vehicle:<\/strong> Sports\/luxury  <\/p>\n\n<p><strong>Must haves:<\/strong> Awd, leather seats &lt;100k miles  <\/p>\n\n<p><strong>Desired transmission (auto\/manual, etc):<\/strong> auto  <\/p>\n\n<p><strong>Intended use:<\/strong> Daily driver  <\/p>\n\n<p><strong>Vehicles you&#39;ve already considered:<\/strong> Infinity g35\/g37, Ford Taurus SHO, lincoln mks ecoboost,  <\/p>\n\n<p><strong>Is this your 1st vehicle:<\/strong> no  <\/p>\n\n<p><strong>Do you need a Warranty:<\/strong> no  <\/p>\n\n<p><strong>Can you do Minor work on your own vehicle:<\/strong> yes  <\/p>\n\n<p><strong>Can you do Major work on your own vehicle:<\/strong> no way  <\/p>\n\n<p><strong>Additional Notes:<\/strong> College student, just totaled my first car which was an 08 Toyota sienna. Would like something relatively reliable to DD but also quick, something that pulls hard but has a nice interior still. (Side note if anyone has the v6 ecoboost motor how reliable is it?)<\/p>\n<\/blockquote>\n<\/div>","10":"<div class=\"md\"><p><strong>Location:<\/strong> Midwest USA<strong>Price range:<\/strong> Under $7,000<strong>Lease or Buy:<\/strong> Buy<strong>New or used:<\/strong> Used<strong>Type of vehicle:<\/strong> Small SUV<strong>Must haves:<\/strong> 4wd<strong>Desired transmission (auto\/manual, etc):<\/strong> Auto<strong>Intended use:<\/strong> Daily Driver<strong>Vehicles you&#39;ve already considered:<\/strong> early 2000s RAV4, CR-V<strong>Is this your 1st vehicle:<\/strong> No<strong>Do you need a Warranty:<\/strong> No<strong>Can you do Minor work on your own vehicle:<\/strong> Yes<strong>Can you do Major work on your own vehicle:<\/strong> No<strong>Additional Notes:<\/strong> Looking for a tiny SUV with 4wd, good for some soft roading and also daily driving. I really like the late 90s RAV4, or even something the size of a Tracker, stuff like that.<\/p>\n<\/div>","11":"<div class=\"md\"><p>[gel\u00f6scht]<\/p>\n<\/div>","12":"<div class=\"md\"><p>Hi I got my license a year ago but because of the law in my country I can&#39;t drive a car that has more than 109 hp until I&#39;m 21, so I was thinking what are some cool\/good cars under 109 hp.<\/p>\n<\/div>","13":"<div class=\"md\"><p>Location: Seattle, WA<\/p>\n\n<p>Price range: $10K max<\/p>\n\n<p>Lease or Buy: Buy<\/p>\n\n<p>New or used: Used<\/p>\n\n<p>Type of vehicle: (Truck, Car, Sports Car, Sedan, Crossover, SUV, Racecar, Luxury etc.) Wagon or SUV<\/p>\n\n<p>Must haves: (4x4, AWD, Fuel efficient, Navigation, Turbo, V8, V6, Trunk space, Smooth ride, Leather etc.) 4x4 or AWD<\/p>\n\n<p>Desired transmission (auto\/manual, etc): Auto<\/p>\n\n<p>Intended use: (Daily Driver, Family Car, Weekend Car, Track Toy, Project Car, Work Truck, Off roading etc.) Weekend trip car<\/p>\n\n<p>Vehicles you&#39;ve already considered: Everything Subaru, Jeep Wrangler, 4Runner<\/p>\n\n<p>Is this your 1st vehicle: No<\/p>\n\n<p>Do you need a Warranty: No<\/p>\n\n<p>Can you do Minor work on your own vehicle: (fluids, alternator, battery, brake pads etc) No<\/p>\n\n<p>Can you do Major work on your own vehicle: (engine and transmission, timing belt\/chains, body work, suspension etc ) No<\/p>\n\n<p>Additional Notes: This will be my only car but I do not drive to work. I want a car that I can take off the beaten path. I have been looking at Subaru&#39;s and think that they would probably be my best bet. I like to think I would enjoy more offroading and Overlanding which makes the Jeep seem cool (also really like the look) but most likely I won&#39;t do much more than drive down some crappy roads to get to a spot to fish or hike. I drove a Tahoe from Highschool through College and then I got a Miata for my first car, now I want something that can hold more stuff and reach some more obscure places.<\/p>\n<\/div>","14":"<div class=\"md\"><blockquote>\n<p><strong>Location:<\/strong> (Specify your country or region)<br\/>\nUSA , cali<\/p>\n\n<p><strong>Price range:<\/strong> (Minimum-Maximum in your local currency)<br\/>\n25 to 50k<\/p>\n\n<p><strong>Lease or Buy:<\/strong><br\/>\nBuy<\/p>\n\n<p><strong>New or used:<\/strong><br\/>\nUsed<\/p>\n\n<p><strong>Type of vehicle:<\/strong> (Truck, Car, Sports Car, Sedan, Crossover, SUV, Racecar, Luxury etc.)<br\/>\nSports car<\/p>\n\n<p><strong>Must haves:<\/strong> (4x4, AWD, Fuel efficient, Navigation, Turbo, V8, V6, Trunk space, Smooth ride, Leather etc.)<br\/>\nRwd, 2 doors, manual, good steering feedback, good handling, looks good, 1990 or newer, very raw, visceral, and aggressively sporty. Impractical, uncomfortable and small is ok. Fast is preferred but not number 1 priority, driving dynamics is number 1. Not planning to mod at all.<\/p>\n\n<p><strong>Desired transmission (auto\/manual, etc):<\/strong><br\/>\nManual only<\/p>\n\n<p><strong>Intended use:<\/strong> (Daily Driver, Family Car, Weekend Car, Track Toy, Project Car, Work Truck, Off roading etc.)<br\/>\nWeekend car<\/p>\n\n<p><strong>Vehicles you&#39;ve already considered:<\/strong><br\/>\nRx7fd, lotus elise, corvette, 911, cayman\/boxster<\/p>\n\n<p><strong>Is this your 1st vehicle:<\/strong><br\/>\nNo<\/p>\n\n<p><strong>Do you need a Warranty:<\/strong><br\/>\nNo<\/p>\n\n<p><strong>Can you do Minor work on your own vehicle:<\/strong> (fluids, alternator, battery, brake pads etc)<br\/>\nYes<\/p>\n\n<p><strong>Can you do Major work on your own vehicle:<\/strong> \nNo<\/p>\n<\/blockquote>\n<\/div>","15":"<div class=\"md\"><p>Looking at a 18 Corolla vs 17 or 18 civic. More into the civic anyone reason to consider a Corolla more is the civic good long term?<\/p>\n<\/div>","16":"<div class=\"md\"><p>Location: U.S.<\/p>\n\n<p>Is there any other cars that have a feature like BMW&#39;s Emergency Stop Assist? I&#39;m not talking about autonomous emergency braking, I&#39;m talking about BMW&#39;s system in particular (in their Driving Assistance Pro Package) that allows the driver to pull a switch to bring the car to a controlled stop. Does any other make have this feature or does anyone know of this feature coming out soon on another make? Thanks.<\/p>\n<\/div>","17":"<div class=\"md\"><p>In Canada - below $5k -<\/p>\n\n<p>Looking to purchase a cheap, good looking car (first car)<\/p>\n\n<p>I\u2019m looking at buying a used (olderish) vehicle. \nI\u2019m super into the look of those old BMW\u2019s and Mercedes, 1990-2003 era, however I heard maintenance, repairs, and gas can be a b!!!!. I\u2019m looking for something with the same look and feel, however maybe a little more reliable? Cheaper? Even if I have to modify it a bit and put in some work as I am looking for a kind of project car? \nI\u2019m Into modifying too!!<\/p>\n\n<p>Thanks!<\/p>\n<\/div>","18":"<div class=\"md\"><p>Location: SoCal<\/p>\n\n<p>Price range: 15,000 - can stretch a little<\/p>\n\n<p>Lease or Buy: buy<\/p>\n\n<p>New or used: uses<\/p>\n\n<p>Type of vehicle: small SUV\/crossover<\/p>\n\n<p>Must haves: reliability<\/p>\n\n<p>Desired transmission: Auto or Stick<\/p>\n\n<p>Intended use: ultra high mileage driver plus commuting (major road tripper: hwy miles)<\/p>\n\n<p>Vehicles you&#39;ve already considered:  Mazda CX5, Acura RDX<\/p>\n\n<p>Is this your 1st vehicle: no<\/p>\n\n<p>Do you need a Warranty: not really<\/p>\n\n<p>Can you do Minor work on your own vehicle: very minor<\/p>\n\n<p>Can you do Major work on your own vehicle: no<\/p>\n\n<p>&#x200B;<\/p>\n\n<p>want reliability and more room, my 21 y.o. BMW is hosed (got it for a few hundred, tho), need ride pretty quick. Driven cross country at least 20 times since late 90s and want long haul reliability. City commute is about 20 miles a day. I run up huge mileage (70K in 3 years on the old BMW, 275K on my last Civic, 290K on the Civic before that, 335K on Nissan P\/U) Really don&#39;t like Civics anymore, want to be able to haul decent camping gear, bike, inflatable kayak, plus stuff around town for DIY home projects). With Covid still around, still expect major road trips this year, too.<\/p>\n\n<p>&#x200B;<\/p>\n\n<p>Just want to see if there is any dark horse vehicle out there to consider (Hyundai Kona?)<\/p>\n<\/div>","19":"<div class=\"md\"><p>Location: Bedford, UK<\/p>\n\n<p>Price range - Max \u00a33.5k (could stretch to 4K)<\/p>\n\n<p>Buy<\/p>\n\n<p>Used<\/p>\n\n<p>Hatchback (small preferably)<\/p>\n\n<p>Must have - air con and aux would be a bonus not not overly fussed <\/p>\n\n<p>Automatic <\/p>\n\n<p>Town car - probably wouldn\u2019t be daily use <\/p>\n\n<p>Already considering - Toyota Yaris, Ford Fiesta, Toyota \naygo, golf (still considering all of these though just don\u2019t know too much about them) <\/p>\n\n<p>This is my first vehicle <\/p>\n\n<p>I can\u2019t do minor or major works I don\u2019t know about cars.<\/p>\n\n<p>Additional- my bf is 6\u201d5 so I would like him to be able to fit comfortably in the passenger seat<\/p>\n<\/div>","20":"<div class=\"md\"><p><strong>Location:<\/strong> Seattle<\/p>\n\n<p><strong>Price range:<\/strong> 3k - 7k<\/p>\n\n<p><strong>Lease or Buy:<\/strong> Buy<\/p>\n\n<p><strong>New or used:<\/strong> Used<\/p>\n\n<p><strong>Type of vehicle:<\/strong> Car - sedan, coupe, wagon, hatchback<\/p>\n\n<p><strong>Must haves:<\/strong> Fuel Efficient, Reliable, AC would be nice<\/p>\n\n<p><strong>Desired transmission:<\/strong> Auto<\/p>\n\n<p><strong>Intended use:<\/strong> Commuter<\/p>\n\n<p><strong>Vehicles you&#39;ve already considered:<\/strong> 90&#39;s Hondas, 90&#39;s Toyotas, early 2010&#39;s hyundai and Kia<\/p>\n\n<p><strong>Is this your 1st vehicle:<\/strong> No<\/p>\n\n<p><strong>Do you need a Warranty:<\/strong> No<\/p>\n\n<p><strong>Can you do Minor work on your own vehicle:<\/strong> Yes<\/p>\n\n<p><strong>Can you do Major work on your own vehicle:<\/strong> No<\/p>\n\n<p><strong>Additional Notes:<\/strong> I just got a new job and my commute is going to go from 0 to 60 miles round trip in heavy traffic. I don&#39;t want to put the miles on my nice cars so I want a cheap (both to own and purchase) car that will get me to and from work.<\/p>\n\n<p>Used car prices seem crazy high right now so I&#39;d like to find the undervalued cars. i.e Ford that doesn&#39;t have the powershift transmission, Nissan that doesn&#39;t have the JATCO CVT, unusually reliable chevy etc.<\/p>\n<\/div>","21":"<div class=\"md\"><p>Location: Midwest USA<\/p>\n\n<p>Price range: &lt; $20k<\/p>\n\n<p>Lease or Buy: Buy<\/p>\n\n<p>New or used: Used<\/p>\n\n<p>Type of vehicle: Sports coupe\/sedan<\/p>\n\n<p>Must haves: RWD, fun<\/p>\n\n<p>Desired transmission: Manual only<\/p>\n\n<p>Intended use: Daily driver<\/p>\n\n<p>Vehicles you&#39;ve already considered: Mustang GT, Camaro (LT1?), brz\/frs\/86, e90 M3, M235i<\/p>\n\n<p>Must haves: Back seats<\/p>\n\n<p>Is this your 1st vehicle: No<\/p>\n\n<p>Do you need a Warranty: No<\/p>\n\n<p>Can you do Minor work on your own vehicle: Yes<\/p>\n\n<p>Can you do Major work on your own vehicle: Yes<\/p>\n\n<p>Additional Notes: Looking to possibly replace my VN as my daily. Don&#39;t want to go to another fwd hot hatch as I don&#39;t think it would be quite worth it for me to switch. I have a child so I have to have a back seat in the rare chance that she would need to be in this car so unfortunately no Cayman or Z cars.<\/p>\n<\/div>","22":"<div class=\"md\"><p><strong>Want to buy car in coming month.<\/strong> <\/p>\n\n<p><strong>Location:<\/strong> USA, Seattle, WA<\/p>\n\n<p><strong>Price range:<\/strong> Min.35,000$ to Max.40,000$ <\/p>\n\n<p><strong>Lease or Buy:<\/strong> No lease. <\/p>\n\n<p><strong>New or used:<\/strong> Open for new 2021 or used 2020 models<\/p>\n\n<p><strong>Type of vehicle:<\/strong> 8 seater SUV<\/p>\n\n<p><strong>Must haves:<\/strong> AWD, Leather, Lane assist, security features.  <\/p>\n\n<p><strong>Desired transmission (auto\/manual, etc):<\/strong> Auto<\/p>\n\n<p><strong>Intended use:<\/strong> Family Car, Weekend Car: As we are planning to have this as second car and mostly use small car for local use. Sometimes daily if require.<\/p>\n\n<p><strong>Vehicles you&#39;ve already considered:<\/strong> Toyota Highlander XLE, Honda Pilot Turing <\/p>\n\n<p><strong>Is this your 1st vehicle:<\/strong> Yes. First SUV model<\/p>\n\n<p><strong>Do you need a Warranty:<\/strong> Not concerned about it as I am looking for almost 2020 and 2021 models and hope they will come with valid factory warranty.<\/p>\n\n<p><strong>Can you do Minor work on your own vehicle: (fluids, alternator, battery, brake pads etc):<\/strong> NO<\/p>\n\n<p><strong>Can you do Major work on your own vehicle: (engine and transmission, timing belt\/chains, body work, suspension etc ) :<\/strong> NO<\/p>\n\n<p><strong>Additional Notes<\/strong>:<\/p>\n\n<p>I am living in Seattle WA and this beautiful area needs good SUV+AWD to take advantage of all seasons around. I am missing that part without having valid car. After looking through Toyota and Honda, I am settling down on Honda pilot turing model as it will be value addition for the money. I have taken test drive of it and really liked it. I also took test drive of Toyota Highlander XLE and it felt small at third row and cost is very high for hybrid and without hybrid as well. On the other side, Turing comes with 0% APR financing + way less than the hybrid. Hence I am inclided to turing. <\/p>\n\n<p>I am planning to hold on this car atleast for next 6 years!<\/p>\n\n<p>If you folks have some better suggestions with respect price, features, new vs used, electric(?), that I am missing, please let me know. <\/p>\n\n<p>Thanks In Advance.<\/p>\n<\/div>","23":"<div class=\"md\"><p>Location: Midwest, USA<\/p>\n\n<p>Price range: $15k-18k USD (maybe up to $20k if I wait\/save a bit) <\/p>\n\n<p>Lease or Buy: Buy (or lease to own) <\/p>\n\n<p>New or used: Used<\/p>\n\n<p>Type of vehicle: Sports Hatch, Wagon, or very small SUV\/crossover<\/p>\n\n<p>Must haves: Heated Leather seats, Turbo, AWD (preferred), enough trunk space for hauling lumber for occasional home DIY<\/p>\n\n<p>Desired transmission (auto\/manual, etc): Any<\/p>\n\n<p>Intended use:  Daily driver, weekend warrior, can handle snow, occasional project car likely lol<\/p>\n\n<p>Vehicles you&#39;ve already considered: Saab TurboX Wagon, Mazda 3 hatch, Volvo v60, open to many others<\/p>\n\n<p>Is this your 1st vehicle: no, currently drive a 2003 Saab 9-3 <\/p>\n\n<p>Do you need a Warranty: No<\/p>\n\n<p>Can you do Minor work on your own vehicle: Yes<\/p>\n\n<p>Can you do Major work on your own vehicle: Mostly <\/p>\n\n<p>Additional Notes: I fell in love with Turbos when I got my Saab. Would love to upgrade to something newer and with AWD for winter. I don&#39;t particularly love the look of Saab wagons, so I&#39;m interested in branching out. Wife wants an SUV, but after driving a GMC Yukon years ago, I don&#39;t want to go back. Looking to &quot;compromise&quot; with a turbo hatch that can hopefully hold everything we need.<\/p>\n<\/div>","24":"<div class=\"md\"><p>Location: Victoria, Australia<\/p>\n\n<p>Price Range: $12k AUD or $9k USD<\/p>\n\n<p>Lease or Buy: Buy<\/p>\n\n<p>New or used: Used<\/p>\n\n<p>Type of vehicle: Any<\/p>\n\n<p>Must Haves: Fuel efficient, smooth ride, reliable, good looking<\/p>\n\n<p>Desired Transmission: Auto<\/p>\n\n<p>Intended use: Daily driver<\/p>\n\n<p>Vehicles you&#39;ve already considered: Hyundai i30, Mazda 3, Honda city, holden commodore, Volkswagen Golf, all seem like decent options but open to more<\/p>\n\n<p>Is this your 1st vehicle: Yes<\/p>\n\n<p>Do you need a warranty: No<\/p>\n\n<p>Can you do minor work on your vehicle: Not currently but will learn<\/p>\n\n<p>Can you do major work on your vehicle: No<\/p>\n\n<p>Cheers<\/p>\n<\/div>","25":"<div class=\"md\"><blockquote>\n<p><strong>Location:<\/strong> US - Midwest<br\/>\n<strong>Price range:<\/strong> Under $7000 USD<br\/>\n<strong>Lease or Buy:<\/strong> Buy<br\/>\n<strong>New or used: Used<\/strong><br\/>\n<strong>Type of vehicle:<\/strong> four-seat enthusiast vehicle<br\/>\n<strong>Must haves:<\/strong> Be reasonably fun on track (NOT racing by any means) with minimal modification. I&#39;m fine adding a big brake kit, better wheels\/tires..but if a car has serious flaws that require the aftermarket to correct to become a dependable track toy (say the aftermarket oil pan needed on a Toyota 2ZZ) I&#39;m not feeling like doing that work.<br\/>\n<strong>Desired transmission (auto\/manual, etc):<\/strong>Must have manual or quality dual-clutch auto<br\/>\n<strong>Intended use:<\/strong> Daily - but I have other vehicles so I won&#39;t be devastated if it needs to sit for a repair. It will see the track half a dozen times a year.<br\/>\n<strong>Vehicles you&#39;ve already considered:<\/strong> Mk5 GTI, E46, R53 Mini Cooper S<br\/>\n<strong>Is this your 1st vehicle:<\/strong> NO<br\/>\n<strong>Do you need a Warranty:<\/strong> No<br\/>\n<strong>Can you do Minor and majorwork on your own vehicle<\/strong> Yes, both major and minor. Don&#39;t feel like doing bodywork, though.<br\/>\n<strong>Additional Notes:<\/strong> No Miatas. I don&#39;t fit a Miata that has a rollbar unless it has a floor drop - which falls under the &quot;no bodywork&quot; clause. Also, while I&#39;d love to get into the Honda\/Acura ecosystem, too many of them have been badly hacked by a combination of F&amp;F, stancelyfe, and elementary-school mechanics for me to seriously consider most. If I could find a clean EK Si or DC GS-R, I&#39;d jump on it...but rust be the name of the game around here on the big H.<\/p>\n<\/blockquote>\n<\/div>","26":"<div class=\"md\"><p>I&#39;m looking for a new car and my budget is really low($2000) so not many options in my area except for one right now which is a Volvo 240 with 225k+ miles on it. They said they&#39;ve our recent motor mounts, tranny mount, and recent timing belt. As well as saying the AC doesn&#39;t cool unless charged. <\/p>\n\n<p>That also said &quot;The motor mounts, timing belt, and oil changes were handled by me.\u00a0\u00a0 Things I haven&#39;t dealt with: the rear struts make a clunking sound that would go away with new bushings; it could benefit from a valve adjustment, which would also take care of an oil leak at the valve cover gasket.\u00a0 I keep an eye on the coolant level as there is a slight leak in the coolant system (maybe bypass pipe on rt side of motor) but it is very gradual.<\/p>\n\n<p>It&#39;s a 28 year old car, I drive it to work occasionally (50 mile round trip) so it gets city and highway exercise.&quot;<\/p>\n\n<p>I don&#39;t know what nearly any of this means. I want to learn how to maintain whatever car I get but this one seems old. The pictures of it look very nice. Is there anyone that can just tell me if these issues are heavy investments, or what kind of things would I have to worry about with this car if I got it.<\/p>\n<\/div>","27":"<div class=\"md\"><p><strong>Location:<\/strong> Upstate NY<br\/>\n<strong>Price range:<\/strong>  15-28k<br\/>\n<strong>Lease or Buy: Either<\/strong><br\/>\n<strong>New or used: Either<\/strong><br\/>\n<strong>Type of vehicle:<\/strong> Racecar<br\/>\n<strong>Must haves:<\/strong> AWD and pretty fun. (Snow and all)<br\/>\n<strong>Desired transmission (auto\/manual, etc): Automatic<\/strong><br\/>\n<strong>Intended use: Fun Daily Driver<\/strong><br\/>\n<strong>Vehicles you&#39;ve already considered: FRS (But to slow), STI (Don&#39;t know if I like the looks), leasing Model 3 (since my apartment comes with a charger)<\/strong><br\/>\n<strong>Is this your 1st vehicle: First car I buy for myself<\/strong><br\/>\n<strong>Do you need a Warranty: Not really<\/strong><br\/>\n<strong>Can you do Minor work on your own vehicle:<\/strong> YES<br\/>\n<strong>Can you do Major work on your own vehicle: No but that&#39;s due to living in an apartment and not having a garage but an outdoor gated lot.<\/strong><br\/>\n<strong>Additional Notes:<\/strong><\/p>\n\n<p>&#x200B;<\/p>\n\n<p>This will be my car for the next 2 years. After 2 years I want get a Supra and so this will be my &quot;save for a supra fun cheap car&quot;. I plan on selling it and lose a bit of money but I can take a 10k loss for the car I actually want. I will plan on buying that car in cash so the lower the price of this guy the better as long as it&#39;s fun. I thought about leasing the tesla since it&#39;s cheaper in the long run tbh. No Maintanence, not having to pay for the electricity and so on.<\/p>\n<\/div>","28":"<div class=\"md\"><p>Location: Oregon<\/p>\n\n<p>Price range: $10k max<\/p>\n\n<p>Lease or Buy: Buy<\/p>\n\n<p>New or used: Used<\/p>\n\n<p>Type of vehicle: Sports car<\/p>\n\n<p>Must haves: RWD\/AWD<\/p>\n\n<p>Desired transmission (auto\/manual, etc): Manual<\/p>\n\n<p>Intended use: Weekend\/Project Car<\/p>\n\n<p>Vehicles you&#39;ve already considered: Mustang, F-Body, 944, 3-Series, anything worth driving that is not a Miata.<\/p>\n\n<p>Is this your 1st vehicle: No<\/p>\n\n<p>Do you need a Warranty: No<\/p>\n\n<p>Can you do Minor work on your own vehicle: Yes<\/p>\n\n<p>Can you do Major work on your own vehicle: No but willing to invest in the time and tools to learn<\/p>\n\n<p>Basically, I recently changed my DD over from a small car to an SUV and I am missing the fun factor - so I&#39;m looking to scratch the inner 16-year-olds itch and get something with a stick shift that can convert money into sound and joy. I just don&#39;t want to be a Miata guy. I have friends with amazing NAs and NBs, but I&#39;m 6&#39;3&quot; and have no desire to drive a tiny car.<\/p>\n<\/div>","29":"<div class=\"md\"><p>Aha, I asked a question here earlier. I decided a white car is fine for me.<\/p>\n\n<p>The car only has 37K miles. 2015 MK7 GTI. The service record is on the carfax, and they are totally fine with me getting it inspected. I don&#39;t really have any worries with it, but the car needs an oil change. The car is in pristine shape.<\/p>\n\n<p>Is a pre-purchase inspection worth it for a car this new? I&#39;m fine paying the $100 for it, but my mechanic shop is only open M-F. Would be a pain in the ass to organize, since I work those days.<\/p>\n<\/div>","30":"<div class=\"md\"><p>Location: Washington United States\nPrice Range: $1-10,000 USD\nBuy\nUsed\nSedan? Luxury? SUV?\nMust haves: I\u2019m a real estate agent who loves to hike adventure and snowboard. I currently drive a 2 seat Audi TT and it doesn\u2019t check any of my boxes anymore although it\u2019s a fun little car. I need 4wd to get to the mountain. Something reliable. And a classy somewhat nice interior with a smooth ride for clients. Knowing my budget I will have to make some sacrifices but any insight is helpful. Maybe Audi Mercedes bmw? Most important is 4wd and budget\nTransmission: either or\nIntended use: showing clients, daily driver, and mountain car\nVehicles I\u2019ve considered: Audi A4?\nNot my first vehicle \nNo warranty \nI can do minor work\nI cannot do major work<\/p>\n<\/div>","31":"<div class=\"md\"><p><strong>Location:<\/strong> US \/ Western Massachusetts (i.e. not Boston)<\/p>\n\n<p><strong>Price range:<\/strong> 0 - 35k-ish (little over is ok) <\/p>\n\n<p><strong>Lease or Buy:<\/strong> Buy. I put on very few miles even before COVID and WFH. My current lease didn&#39;t even use 1\/3rd of the miles I could have used. I&#39;d rather ride my bike. Don&#39;t judge me.<\/p>\n\n<p><strong>New or used:<\/strong> Used, but lightly. 20k-ish miles or less. Just looking to avoid paying for the depreciation hit. If there&#39;s an amazing deal on a new car I&#39;d still be interested in hearing about it though.<\/p>\n\n<p><strong>Type of vehicle:<\/strong> Sporty Luxury-esque car. Door count doesn&#39;t matter. Hatches \/ Fastbacks are fine but probably not a wagon. I don&#39;t have kids or anything but I will need to put a bike roof rack on it. I like Euro car makes in general but I am open minded.<\/p>\n\n<p><strong>Must haves:<\/strong> AWD, Moonroof\/Sunroof\/Panarama, Luxury-esque interior but not grandpa&#39;s car if that makes sense? Infotainment with Android support.<\/p>\n\n<p><strong>Desired transmission (auto\/manual, etc):<\/strong> Auto on this one. Some form of manu-matic would be appreciated but not required.<\/p>\n\n<p><strong>Intended use:<\/strong> Daily in all 4 Massachusetts seasons. I don&#39;t mind swapping summers to snows seasonally. Don&#39;t want to roll up to the office looking like a douchebag or that I&#39;m a 40-something trying to look like I&#39;m 20 again. For example, I love the Subaru WRX for what it is, but it&#39;s a little too boy-racer in design. <\/p>\n\n<p><strong>Vehicles you&#39;ve already considered:<\/strong> I haven&#39;t written these off, they&#39;re my strongest contenders now:<\/p>\n\n<p>Alfa Romeo Giulia <\/p>\n\n<p>Volvo S60<\/p>\n\n<p><strong>Is this your 1st vehicle:<\/strong>  Nope<\/p>\n\n<p><strong>Do you need a Warranty:<\/strong> Sort of?  Some remainder of factory warranty or a CPO would be nice.<\/p>\n\n<p><strong>Can you do Minor work on your own vehicle:<\/strong> I can, but I probably won&#39;t. <\/p>\n\n<p><strong>Can you do Major work on your own vehicle:<\/strong> I can, but I probably won&#39;t.<\/p>\n\n<p><strong>Additionally<\/strong>... I can be in no big hurry if there is something big coming for mid 2021 that fits the bill. I&#39;m hoping to buy around March\/April but I could wait a couple months more if needed.<\/p>\n<\/div>","32":"<div class=\"md\"><p>Hi\nI&#39;m looking for an SUV with a third row.\nBudget is $30k\nSeems like the best options are: 2018ish CPO Honda Pilot, 2018ish CPO Ford Explorer or a 2018ish CPO Chevy Traverse\nI do most of my own maintenance.\nPriorities are safety and reliability. Cargo space important as well. Would prefer an older loaded vehicle versus newer base.\nI&#39;m thinking that I may just go with the best overall deal I can find because all three have their ups and downs. Looking for any input that may help narrow down my choices.\nThanks<\/p>\n<\/div>","33":"<div class=\"md\"><blockquote>\n<p><strong>Location:<\/strong> Midwest USA<br\/>\n<strong>Price range:<\/strong> 10000-18000<br\/>\n<strong>Lease or Buy:  Buy<\/strong><br\/>\n<strong>New or used:  Used<\/strong><br\/>\n<strong>Type of vehicle:<\/strong> SUV or Sports Car<br\/>\n<strong>Must haves:<\/strong><br\/>\n<strong>Desired transmission (auto\/manual, etc):  Manual<\/strong><br\/>\n<strong>Intended use:<\/strong> Daily Driver<br\/>\n<strong>Vehicles you&#39;ve already considered:  Mustang or Jeep Rubicon<\/strong><br\/>\n<strong>Is this your 1st vehicle:  No<\/strong><br\/>\n<strong>Do you need a Warranty:  No<\/strong><br\/>\n<strong>Can you do Minor work on your own vehicle:<\/strong> Yes<br\/>\n<strong>Can you do Major work on your own vehicle:<\/strong> I can do body work<br\/>\n<strong>Additional Notes:<\/strong>  Just got t-boned on the interstate, losing my beloved &#39;07 Mustang I&#39;ve had for 13 years.  Struggling to decide if I should change it up and get a better &quot;snow car&quot; (bounce between Nebraska and Missouri so lots of snow potential) or if I should just try to go with another Mustang.<\/p>\n<\/blockquote>\n<\/div>","34":"<div class=\"md\"><p>Location:USA - Central Florida<\/p>\n\n<p>Price range: 10k-25k<\/p>\n\n<p>Lease or buy: Buy<\/p>\n\n<p>New or used:  Either<\/p>\n\n<p>Type of vehicle: No trucks, other than that not picky<\/p>\n\n<p>Must haves: GPS\/touchscreen, phone connectivity, good gas mileage<\/p>\n\n<p>Desired transmission: Auto<\/p>\n\n<p>Intended use: Daily, road trips<\/p>\n\n<p>Vehicles considered: Too indecisive and ignorant to seriously consider anything :\/<\/p>\n\n<p>Is this your 1st vehicle: No<\/p>\n\n<p>Do you need warranty: No<\/p>\n\n<p>Can you do Minor work on your own vehicle: Yes<\/p>\n\n<p>Can you do major work on your own vehicle: No<\/p>\n\n<p>Additional notes: Car bunked out as soon as I moved down, so desperately need something, but don\u2019t wanna jump on and hate what I get. My social circle is small, and my roommate has a bigger car, so I\u2019m not opposed to a 2 seater. Also, as for the touchscreen, I\u2019m willing to just buy one separately and put it in, so if it\u2019s not included no biggy. I\u2019m a young single dude, so something fun to drive and kinda \u201cshow off\u201d\/play around with would be cool.<\/p>\n<\/div>","35":"<div class=\"md\"><p>Coming here for advice again.<\/p>\n\n<p>I&#39;m about to buy a used car. Private sale. Price agreed upon, subject to inspection.<\/p>\n\n<p>After reading more, and comparing to the ad, I&#39;m pretty sure the car will be up for service like <em>right now.<\/em> It&#39;s the DSG service on a GTI. <\/p>\n\n<p>I&#39;m pretty new to buying used cars. Should I lower my offer, since service will need to be done immediately? Or should I just eat the cost.<\/p>\n\n<p>Want to get the best deal, but also don&#39;t want to be a slime ball.<\/p>\n<\/div>","36":"<div class=\"md\"><p>Mazda 2\/Scion iA\/Yaris iA<\/p>\n\n<p>I was really interested in a 2017 yaris iA, new car, low mileage, in my price range, and a toyota. I would like a car that i can put 200,000+ miles in with no issues, so I thought this was perfect<\/p>\n\n<p>Come to find out, it&#39;s not a toyota, it&#39;s actually a mazda2, everything I&#39;ve read says mazdas newer cars are reliable but I want a car that has the potential to last close to a well maintained corolla\/camry\/accord and is cheap to maintain<\/p>\n\n<p>Did I get fooled by the branding?<\/p>\n<\/div>","37":"<div class=\"md\"><p>Hi everyone, I am the opposite of a car guy :(. I know next to nothing about cars \/ automobiles and would be thankful for any help I can get.<\/p>\n\n<p>I drive Uber 20 hours\/week so gas mileage is important. Perhaps a hybrid? I would <strong>love<\/strong> a vehicle large enough to car camp in as I travel frequently to national forests\/BLM land across the US (long trips, I&#39;m in Midwest). <\/p>\n\n<p><strong>Location:<\/strong> Midwest, USA<\/p>\n\n<p><strong>Price range:<\/strong> $7500 - $8000 max<\/p>\n\n<p><strong>Lease or Buy:<\/strong> Buy<\/p>\n\n<p><strong>New or used:<\/strong> used<\/p>\n\n<p><strong>Type of vehicle:<\/strong> Sedan, Crossover, SUV (the roomier the better)<\/p>\n\n<p><strong>Must haves:<\/strong> Fuel efficient, 2010 or newer <\/p>\n\n<p><strong>Intended use:<\/strong> Daily Driver<\/p>\n\n<p><strong>Do you need a Warranty:<\/strong> no<\/p>\n\n<p><strong>Can you do Minor work on your own vehicle:<\/strong> yes<\/p>\n\n<p><strong>Can you do Major work on your own vehicle:<\/strong> No, but I have $ to pay someone to if needed.<\/p>\n\n<ul>\n<li>#1 priority is good gas mileage<\/li>\n<li><h1>2 priority is roominess\/size (large enough to travel\/car camp with)<\/h1><\/li>\n<li><p>Vehicles I&#39;ve considered: Ford escape, ford fusion, suburu impreza, nissan murano<\/p><\/li>\n<\/ul>\n<\/div>","38":"<div class=\"md\"><p>Buy a Mustang<\/p>\n<\/div>","39":"<div class=\"md\"><p>[gel\u00f6scht]<\/p>\n<\/div>","40":"<div class=\"md\"><p>[UK] My dad wants a new car on lease, not sure what to get.<\/p>\n\n<p>My dad is getting a new car, he wants a small SUV for under \u00a3280 per month<\/p>\n\n<p>Probably about VW T-Cross, Skoda Kamiq size<\/p>\n\n<p>We\u2019ve found a Skoda Kamiq for \u00a3240 a month with a \u00a3700 deposit, but what other options are there?<\/p>\n\n<p>Requirements:<\/p>\n\n<p>Fuel: Petrol<\/p>\n\n<p>Gearbox: Automatic<\/p>\n\n<p>Initial Rental: \u00a31000max\/3months<\/p>\n\n<p>Max monthly payout: \u00a3280<\/p>\n<\/div>","41":"<div class=\"md\"><p><strong>Location:<\/strong> Pittsburgh PA but also willing to travel far to find a good car<\/p>\n\n<p><strong>Price range:<\/strong> $7,000 max<\/p>\n\n<p><strong>Lease or Buy:<\/strong> Buy<\/p>\n\n<p><strong>New or used:<\/strong> Used<\/p>\n\n<p><strong>Type of vehicle:<\/strong> Sedan<\/p>\n\n<p><strong>Must haves:<\/strong> Good reliability and safety. Smooth ride would be nice too but I want to be realistic considering my budget.<\/p>\n\n<p><strong>Desired transmission (auto\/manual, etc):<\/strong> Auto<\/p>\n\n<p><strong>Intended use:<\/strong> Weekend car, long distance driving (think 20 mile trips one way), and occasional road trips across and outside the state<\/p>\n\n<p><strong>Vehicles you&#39;ve already considered:<\/strong> 2015 Hyundai Elantra with 132,900 miles for $5,500 - <a href=\"https:\/\/www.cars.com\/vehicledetail\/detail\/828814573\/overview\/\">listing<\/a> \/\/  2010 Toyota Corolla with 131,600 miles, $5,490 - <a href=\"https:\/\/www.cars.com\/vehicledetail\/detail\/831862175\/overview\/\">listing<\/a><\/p>\n\n<p><strong>Is this your 1st vehicle:<\/strong> Yes! I am very recently licensed.<\/p>\n\n<p><strong>Do you need a Warranty:<\/strong> No<\/p>\n\n<p><strong>Can you do Minor work on your own vehicle:<\/strong> Not at <em>all<\/em>. I am clueless and want a car that won&#39;t break down in ways I don&#39;t know how to deal with.<\/p>\n\n<p><strong>Can you do Major work on your own vehicle:<\/strong> Nope.<\/p>\n\n<p><strong>Additional Notes:<\/strong> Do you think the cars I am thinking of are good first cars? Are the ones I found reasonably priced? Thanks!<\/p>\n<\/div>","42":"<div class=\"md\"><p>Location: Europe (Romania)<\/p>\n\n<p>Price range: 4000 to 7000 max 8000 Euros (maybe more but I want to have some money left for upgrades, or maybe the car and the needed upgrades can fit in this range)<\/p>\n\n<p>Lease or Buy:  Buy<\/p>\n\n<p>New or used: Used<\/p>\n\n<p>Type of vehicle:  SUV,<\/p>\n\n<p>Must haves: 4x4, AWD, Fuel efficient,<\/p>\n\n<p>Desired transmission : manual<\/p>\n\n<p>Intended use: Daily Driver, Off roading <\/p>\n\n<p>Vehicles you&#39;ve already considered: Suzuki Jimmy (but it&#39;s 2 door, that&#39;s my main problem about it being a daily driver)<\/p>\n\n<p>Is this your 1st vehicle: <\/p>\n\n<p>Do you need a Warranty: No<\/p>\n\n<p>Can you do Minor work on your own vehicle: Absolutely<\/p>\n\n<p>Can you do Major work on your own vehicle: I might try to get a friend to help me, he has more experience than me and a better shop and tools etc.<\/p>\n\n<p>A couple more details, i would prefer to be a smaller engine size 2.0 liter or below that because in my country the annual tax for engine&#39;s that are above 2.0 liter is quite expensive, I can maybe workaround this and somehow afford to pay it for a 2.5 liter engine if you guys recommend it but I don&#39;t think it&#39;s necessary because I don&#39;t do a lot of km\/miles and no highway (we have quite bad road&#39;s).\n I mostly drive around 15km\/10 miles a day(some days maybe les) maybe triple that in some days but that&#39;s not frequently (I&#39;m close to work, gym, store&#39;s, city and all) and that&#39;s why I would prefer a gas engine because a diesel would not even reach functioning temperature and from what I know they are not meant for this kind of driving.\nIt doesn&#39;t need to be fast either, mostly city\/village driving(which in my case is quit slow , traffic and bad road&#39;s)between 40, 80 km\/h \/ 25, 50mph.\nThe main thing it&#39;s that I want it to be a petrol engine 4 door if possible not very big engine decent consumption, that u can daily driver and take it to light to medium off-road, to forest\/mountain roads and take it off the beaten track but not something very hard core(maybe in the future but this is not important).<\/p>\n\n<p>Sorry for the wall of text\ud83d\ude01.<\/p>\n<\/div>","43":"<div class=\"md\"><p>Location: US - Seattle<\/p>\n\n<p>Price range: $0 - $80,000<\/p>\n\n<p>Lease or Buy: Buy<\/p>\n\n<p>New or used: New<\/p>\n\n<p>Type of vehicle: Sports Car<\/p>\n\n<p>Must haves: ~4.2 0-60; Nice handling<\/p>\n\n<p>Desired transmission (auto\/manual, etc): Automatic<\/p>\n\n<p>Intended use: Daily Driver<\/p>\n\n<p>Vehicles you&#39;ve already considered: 2021 Corvette (don&#39;t feel like waiting 1 year and paying 10k over MSRP); Lotus Evora (a bit too pricy); Dodge Challenger Hellcat (can&#39;t decide if I&#39;ll like american muscle)<\/p>\n\n<p>Is this your 1st vehicle: No<\/p>\n\n<p>Do you need a Warranty: No<\/p>\n\n<p>Can you do Minor work on your own vehicle: No<\/p>\n\n<p>Can you do Major work on your own vehicle: No<\/p>\n\n<p>Additional Notes: No<\/p>\n<\/div>","44":"<div class=\"md\"><p><strong>Location:<\/strong> New York City<\/p>\n\n<p><strong>Price range:<\/strong> $35,000 - $47,000<\/p>\n\n<p><strong>Lease or Buy:<\/strong> Lease<\/p>\n\n<p><strong>New or used:<\/strong> New<\/p>\n\n<p><strong>Type of vehicle:<\/strong> SUV, Crossover<\/p>\n\n<p><strong>Must haves:<\/strong> Best possible adaptive cruise control and driving assist features, Comfort<\/p>\n\n<p><strong>Desired transmission (auto\/manual, etc):<\/strong> Auto<\/p>\n\n<p><strong>Intended use:<\/strong> Daily Driver, Work trips, and Weekend trips.<\/p>\n\n<p><strong>Vehicles you&#39;ve already considered:<\/strong> Not many, some on my list to test drive are the Mazda CX5 and the Volvo XC40<\/p>\n\n<p><strong>Is this your 1st vehicle:<\/strong> No<\/p>\n\n<p><strong>Do you need a Warranty:<\/strong> No<\/p>\n\n<p><strong>Can you do Minor work on your own vehicle:<\/strong> (fluids, alternator, battery, brake pads etc) No<\/p>\n\n<p><strong>Can you do Major work on your own vehicle:<\/strong> (engine and transmission, timing belt\/chains, body work, suspension etc ) No<\/p>\n\n<p><strong>Additional Notes:<\/strong> I&#39;m looking for something with best driving assist features in my price range, I do lots of driving so driving assist and comfort are what I&#39;m looking for. <\/p>\n\n<p>Appreciate your thoughts! <\/p>\n\n<p>Thanks!<\/p>\n<\/div>","45":"<div class=\"md\"><p>In USA, Cali. My current car is breaking down and I need a daily driver ASAP but I\u2019m overwhelmed by my choices. I\u2019m looking for something used under 10k that won\u2019t break the bank. I\u2019m not wealthy at all but I\u2019m starting to pick up an interest in cars now that I work in a garage. Bonus points if it looks cool, is fun to drive manual, and isn\u2019t too expensive to repair or even work on myself. I\u2019ve looked at older mustangs. I\u2019ve looked at the Miata but I\u2019m just not a fan of how it looks but love everything else about it. Other car I\u2019ve looked at is the 300zx but it\u2019s hard to find a decent one. What would you suggest? Thank you very much<\/p>\n<\/div>","46":"<div class=\"md\"><p><strong>Location:<\/strong> USA<br\/>\n<strong>Price range:<\/strong> $5000 max<br\/>\n<strong>Lease or Buy: Buy<\/strong><br\/>\n<strong>New or used: Used<\/strong><br\/>\n<strong>Type of vehicle:<\/strong> Honda Civic, maybe a Prius<br\/>\n<strong>Must haves:<\/strong> Fuel efficiency; must be able to tow 1,000 pounds<br\/>\n<strong>Desired transmission (auto\/manual, etc):<\/strong> auto<br\/>\n<strong>Intended use:<\/strong> Daily driver<br\/>\n<strong>Vehicles you&#39;ve already considered:<\/strong> Corolla, Prius<br\/>\n<strong>Is this your 1st vehicle:<\/strong> No<br\/>\n<strong>Do you need a Warranty:<\/strong> No<br\/>\n<strong>Can you do Minor work on your own vehicle:<\/strong> Yes<br\/>\n<strong>Can you do Major work on your own vehicle:<\/strong> Probably not<br\/>\n<strong>Additional Notes:<\/strong> My main question is: what am I probably in for when buying one of these at 130,000 -&gt; 150,000 miles? I&#39;m certain I&#39;ll need to replace the timing belt (probably). Are there any definite replacements I&#39;ll want to do immediately?<\/p>\n<\/div>","47":"<div class=\"md\"><p>Location: virginia<\/p>\n\n<p>Price range: 6,000<\/p>\n\n<p>Lease or Buy: buy<\/p>\n\n<p>New or used: uses<\/p>\n\n<p>Type of vehicle: sedan<\/p>\n\n<p>Must haves: the standard or front wheel etc<\/p>\n\n<p>Desired transmission: whichever one isnt stick shift<\/p>\n\n<p>Intended use: daily, work<\/p>\n\n<p>Vehicles you&#39;ve already considered: honda civic and hinda accord <\/p>\n\n<p>Is this your 1st vehicle: no<\/p>\n\n<p>Do you need a Warranty: I believe so if its necessaey<\/p>\n\n<p>Can you do Minor work on your own vehicle: yes naybe<\/p>\n\n<p>Can you do Major work on your own vehicle: no<\/p>\n\n<p>Additional notes:<\/p>\n\n<p>Getting a used car which one is more worth it? Under $6,000 a 2009 vs 2010.\nHi i need help comparing a 2009 honda civic with 177,880 miles and a 2010 honda accord with 188,952 miles.<\/p>\n\n<p>I already got the honda civic and theres minor appearance damages to it like scratches, etc (ie. Doesny have any mats) and personally I dont like appearance of the car but im wondering if its worth returning for the accord. I only had it for 2 days. The owner didnt even give us the title and let us leave without insuring the car.<\/p>\n\n<p>The accord doesnt have any damages but its 3 owners and high milage.<\/p>\n\n<p>Whats ur opinion? Thanks<\/p>\n<\/div>","48":"<div class=\"md\"><p>In United states North Carolina\nUsed\nLooking to buy\nMust haves: ac and aux, under 200k miles\nPrefer a Japanese made coupe or sedan\nUse: daily driver, project car\nBudget: $5,000\nManual with rwd\nI\u2019ve looked at a Mitsubishi Evo and a mazda RX-7 \n I can do minor maintenance \nNot my first car\nCannot do major maintenance <\/p>\n\n<p>Im looking for a sporty manual car that is fast but nothing crazy, something I can modify easily (if the day comes when I can get another daily, I will want to use this car for track\/drifting) any ideas?<\/p>\n<\/div>","49":"<div class=\"md\"><p>[gel\u00f6scht]<\/p>\n<\/div>","50":"<div class=\"md\"><p><strong>Location: california<\/strong><\/p>\n\n<p><strong>Price range: under 15k<\/strong><\/p>\n\n<p><strong>Lease or Buy: buy<\/strong><\/p>\n\n<p><strong>New or used: used<\/strong><\/p>\n\n<p><strong>Type of vehicle:<\/strong> older sports car<\/p>\n\n<p><strong>Must haves:<\/strong> none<\/p>\n\n<p><strong>Desired transmission (auto\/manual, etc): i dont care<\/strong><\/p>\n\n<p><strong>Intended use:<\/strong> personal car<\/p>\n\n<p><strong>Vehicles you&#39;ve already considered: wrx sti 2001-2005<\/strong><\/p>\n\n<p><strong>Is this your 1st vehicle:yes<\/strong><\/p>\n\n<p><strong>Do you need a Warranty: idk<\/strong><\/p>\n\n<p><strong>Can you do Minor work on your own vehicle:<\/strong> yes<\/p>\n\n<p><strong>Can you do Major work on your own vehicle: no<\/strong><\/p>\n\n<p><strong>Additional Notes: no<\/strong><\/p>\n<\/div>","51":"<div class=\"md\"><p><strong>Location: Chicago, Illinois<\/strong><\/p>\n\n<p><strong>Price range:<\/strong> Max around $12,500<\/p>\n\n<p><strong>Lease or Buy:<\/strong> Buy<\/p>\n\n<p><strong>New or used:<\/strong> Used<\/p>\n\n<p><strong>Type of vehicle:<\/strong> Sedan, Crossover, Sub Compact SUV<\/p>\n\n<p><strong>Must haves:<\/strong> Back Up Camera<\/p>\n\n<p><strong>Desired transmission (auto\/manual, etc):<\/strong> Automatic<\/p>\n\n<p><strong>Intended use:<\/strong> Daily Car <\/p>\n\n<p><strong>Vehicles you&#39;ve already considered:<\/strong> Mazda 3, Honda Civic, Kia Forte, Ford Focus<\/p>\n\n<p><strong>Is this your 1st vehicle:<\/strong> Yes<\/p>\n\n<p><strong>Do you need a Warranty:<\/strong> No<\/p>\n\n<p><strong>Can you do Minor work on your own vehicle: Y<\/strong>es<\/p>\n\n<p><strong>Can you do Major work on your own vehicle:<\/strong> No<\/p>\n\n<p><strong>Additional Notes: N<\/strong>one<\/p>\n<\/div>","52":"<div class=\"md\"><p>[gel\u00f6scht]<\/p>\n<\/div>","53":"<div class=\"md\"><p>Is there a car like toyota celica but with automatic transmission?<\/p>\n\n<p>It doesn&#39;t have to be toyota, but i am looking for that look and feel of celicas around year 2000 give or take.<\/p>\n<\/div>","54":"<div class=\"md\"><p>So new father, my wife\u2019s car is it\u2019s death bed, we wanted to upgrade to a Ford Edge or something similar, can anyone recommend me price for value, a good suv\/ mid size cross over alternative, we aren\u2019t able to pay all cash but have likely 50% down payment<\/p>\n<\/div>","55":"<div class=\"md\"><p><strong>Location:<\/strong> Ontario, Canada<\/p>\n\n<p><strong>Price range:<\/strong> 10-15k CAD<\/p>\n\n<p><strong>Lease or Buy: Buy<\/strong><\/p>\n\n<p><strong>New or used: Used<\/strong><\/p>\n\n<p><strong>Type of vehicle:<\/strong> JDM<\/p>\n\n<p><strong>Must haves:<\/strong> Don&#39;t really have any specific must haves tbh<\/p>\n\n<p><strong>Desired transmission (auto\/manual, etc): Manual 100%<\/strong><\/p>\n\n<p><strong>Intended use:<\/strong> Project Car<\/p>\n\n<p><strong>Vehicles you&#39;ve already considered: Nissan Silvia S13, RX7 3rd Gen(Only issue is the rotary engine).<\/strong><\/p>\n\n<p><strong>Is this your 1st vehicle: Yes<\/strong><\/p>\n\n<p><strong>Do you need a Warranty: Not really<\/strong><\/p>\n\n<p><strong>Can you do Minor work on your own vehicle:<\/strong> Some of it<\/p>\n\n<p><strong>Can you do Major work on your own vehicle: No but that&#39;s what I plan to do with this Project Car<\/strong><\/p>\n\n<p><strong>Additional Notes: This is gonna be my first project car so I don&#39;t wanna get something that would be hard to work on, probably won&#39;t be my only project car because I would probably want to upgrade to something else after a while.<\/strong><\/p>\n<\/div>","56":"<div class=\"md\"><p>Location: Vermont\nPrice range: $20,000-$25,000 to buy<\/p>\n\n<p>Either new or used<\/p>\n\n<p>Type of vehicle: sports car, sedans, maybe van?<\/p>\n\n<p>Must have: awd or 4wd, sunroof, hopefully manual<\/p>\n\n<p>Cars considered: subaru wrx, lexus is250 &amp; 350, toyota corolla, subaru forester, toyota highlander, land cruiser, 4runner, sienna <\/p>\n\n<p>Intended use: hobby driving, daily, road trips, carrying mountain bikes <\/p>\n\n<p>Can do minor work myself <\/p>\n\n<p>I want to realize my dream of owning a wrx that I&#39;ve dreamed for about 20 years now, but I am an avid mountain biker and I understand it&#39;s not the most practical for the sport without a roof rack.  I considered suvs and vans to fit my bikes in and for camping and road trips, but I would really miss my nimble and spirited daily drives to work and weekend cruises if I got out of a small car (currently drive 2011 impreza wagon).  I live in VT and contend with dirt roads, mud, snow and steep hills to-and-from work everyday which necessitate awd and preferably manual transmission.  I enjoy an analog driving experience and would like to avoid lane departure warnings and driving assistance for just a little longer if possible.  Any opinions to help are appreciated, thank you for reading!<\/p>\n<\/div>","57":"<div class=\"md\"><p>Help me choose!<\/p>\n\n<p>Looking for pure driving fun. Must be able to function in snow. This is a car I will learn stick on. I can save a bit of money and go with a Base Mini Cooper f56 2016 and add some mods to it. Or I can spend all and go for a Volkswagen GTI 2017 or a Subaru BRZ 2017.<\/p>\n<\/div>","58":"<div class=\"md\"><p><strong>Location:<\/strong> Indiana<\/p>\n\n<p><strong>Price range:<\/strong> 30-45k USD<\/p>\n\n<p><strong>Lease or Buy:<\/strong> Buy<\/p>\n\n<p><strong>New or used:<\/strong> Either (Sub 40k miles if used)<\/p>\n\n<p><strong>Type of vehicle:<\/strong> SUV<\/p>\n\n<p><strong>Must haves:<\/strong> All wheel drive, fairly recent, sub 5.5 0-60, good stock audio system, Semi-sleeper (no over the top sporty styling like the glc coupe), low-avg insurance (No teslas), semi-reliable (no alfa romeos), must be currently available for sale<\/p>\n\n<p><strong>Desired transmission (auto\/manual, etc):<\/strong> Auto<\/p>\n\n<p><strong>Intended use:<\/strong> Daily driver<\/p>\n\n<p><strong>Vehicles you&#39;ve already considered:<\/strong> Genesis GV70, Ford Bronco, Grand cherokee\/durango SRT, Tesla model Y, Audi Q3, Alfa romeo stelvio, wrangler<\/p>\n\n<p><strong>Is this your 1st vehicle:<\/strong> No<\/p>\n\n<p><strong>Do you need a Warranty:<\/strong> Preferred but not needed<\/p>\n\n<p><strong>Can you do Minor work on your own vehicle:<\/strong> yes<\/p>\n\n<p><strong>Can you do Major work on your own vehicle:<\/strong> no<\/p>\n<\/div>","59":"<div class=\"md\"><p>I know that Alfa Romeo&#39;s aren&#39;t the same tier of car as Maseratis, but do AR&#39;s have similar upkeep costs as Maseratis do? Or are they more comparable to other &quot;high end but not luxury&quot; cars.<\/p>\n\n<p>Sorry if this isn&#39;t the right place for this type of question but felt it didn&#39;t warrant it&#39;s own thread.<\/p>\n<\/div>","60":"<div class=\"md\"><p><strong>Location:<\/strong> Middle Europe<\/p>\n\n<p><strong>Price range:<\/strong> 4-7k Euro<\/p>\n\n<p><strong>Lease or Buy:<\/strong> buy<\/p>\n\n<p><strong>New or used:<\/strong>  used (probably old)<\/p>\n\n<p><strong>Type of vehicle:<\/strong> either a SUV offroad or a Wagon\/bigger hatchback (maybe a sedan)<\/p>\n\n<p><strong>Must haves:<\/strong> Versatility, Fuel efficienty, reliability, sth fun and not ugly as hell.<br\/>\n(if possible sth unique)<\/p>\n\n<p><strong>Desired transmission (auto\/manual, etc):<\/strong>  Manual<\/p>\n\n<p><strong>Intended use:<\/strong> First car, daily <\/p>\n\n<p><strong>Vehicles you&#39;ve already considered:<\/strong> Jeep Cherokee XJ or a Audi A4, Ford Fiesta<\/p>\n\n<p>&#x200B;<\/p>\n\n<p>I know the expectations are a little weird. I just need sth relatively cheap that has some versatility to it, and will be a first car.<\/p>\n<\/div>","61":"<div class=\"md\"><p>Need advice for first car dealership purchase<\/p>\n<\/div>","62":"<div class=\"md\"><ol>\n<li><p>Is a a NMVTIS report the same as a carfax report? Is it legit and does it provide as much info as carfax?<\/p><\/li>\n<li><p>Should I avoid cars that have \u201cexempt from odometer reading\u201d on car title changes??<\/p><\/li>\n<li><p>I assume paying for a pre purchase inspection from a reputable auto shop is the way to go?<\/p><\/li>\n<li><p>Reviews of dealerships important?<\/p><\/li>\n<li><p>What are all the things on a carfax\/auto report that are red flags? (So I know what cars to avoid)<\/p><\/li>\n<li><p>I assume I should avoid dealerships that are very far away since I don\u2019t have a car at the moment because I read being there for a cold startup is important? <\/p><\/li>\n<li><p>Any other tips and advice would be real nice right about now<\/p><\/li>\n<\/ol>\n<\/div>","63":"<div class=\"md\"><p><strong>Location:<\/strong> Florida, US<\/p>\n\n<p><strong>Price range:<\/strong> 14-17k<\/p>\n\n<p><strong>Lease or Buy:<\/strong> buy<\/p>\n\n<p><strong>New or used:<\/strong>  used <\/p>\n\n<p><strong>Type of vehicle:<\/strong> Suv<\/p>\n\n<p><strong>Must haves:<\/strong> Reliable, push to start, decent gas milage<\/p>\n\n<p><strong>Desired transmission (auto\/manual, etc):<\/strong>  automatic<\/p>\n\n<p><strong>Intended use:<\/strong> Daily use<\/p>\n\n<p><strong>Vehicles you&#39;ve already considered:<\/strong> open to any suggestions<\/p>\n<\/div>","64":"<div class=\"md\"><p>Saw a 2013 brz with 48k miles on it but with 4 owners. Has a lot of after market parts and going to go look at it this weekend. I plan on taking it to a local mechanic to inspect it, if everything is okay with the car I plan to buy it (18k). What are y\u2019all\u2019s thoughts?<\/p>\n<\/div>","65":"<div class=\"md\"><p>[gel\u00f6scht]<\/p>\n<\/div>","66":"<div class=\"md\"><p>Even if mechanic says it\u2019s all good?<\/p>\n<\/div>","67":"<div class=\"md\"><p><strong>Location:<\/strong> USA - Midsouth<\/p>\n\n<p><strong>Price range:<\/strong> Ideal :25-30k Willing to go to 35-40k<\/p>\n\n<p><strong>Lease or Buy:<\/strong> Buy<\/p>\n\n<p><strong>New or used:<\/strong> New or CPO<\/p>\n\n<p><strong>Type of vehicle:<\/strong> SUV\/Crossover - NO THIRD ROW<\/p>\n\n<p><strong>Must haves:<\/strong> Fuel Efficient, Tow Capability up to 5000lb, not too big<\/p>\n\n<p><strong>Desired transmission (auto\/manual, etc):<\/strong> Auto<\/p>\n\n<p><strong>Intended use:<\/strong> Daily Driver and towing a camper - Current Camper is only about 1500lb but looking to upgrade to a bigger one soon<\/p>\n\n<p><strong>Vehicles you&#39;ve already considered:<\/strong> Jeep Grand Cherokee, VW Atlas Cross Sport<\/p>\n\n<p><strong>Is this your 1st vehicle:<\/strong> No<\/p>\n\n<p><strong>Do you need a Warranty:<\/strong>  Yes - hoping for a good warranty - especially if it&#39;s CPO<\/p>\n\n<p><strong>Can you do Minor work on your own vehicle:<\/strong> Yeah<\/p>\n\n<p><strong>Can you do Major work on your own vehicle:<\/strong> No thank you<\/p>\n\n<p><strong>Additional Notes:<\/strong> I plan on towing pretty often, at least once a month and probably more. So I want something that can handle that, but also not be so poor in MPG that it stops me from going places. I like room in the cargo for my dogs, but don&#39;t want to drive a boat. I&#39;ve always had small sedans (current is a VW Golf) so I do not want something massive. No trucks. Extra towing gadgets would be nice, I&#39;m not experienced with it<\/p>\n<\/div>","68":"<div class=\"md\"><p>[entfernt]<\/p>\n<\/div>","69":"<div class=\"md\"><p>How dumb of an idea is it to paint a brand new truck? I&#39;m looking for a super specific configuration of F150 and adding my color preference on top of that is going to make the search take much longer. Am I a complete idiot for considering jumping on the next one I see that has everything except the color and is a few grand cheaper than it should be, then just take that money and get it painted the factory color I wanted?<\/p>\n<\/div>","70":"<div class=\"md\"><p>Location: USA \/ NW Indiana<\/p>\n\n<p>Price range: 25 - 35k range<\/p>\n\n<p>Lease or Buy: Buy<\/p>\n\n<p>New or used: Leaning CPO but would consider new<\/p>\n\n<p>Type of vehicle: (Truck, Car, Sports Car, Sedan, Crossover, SUV, Racecar, Luxury etc.) Small - Midsize Luxury SUV (no thrid row)<\/p>\n\n<p>Must haves: (4x4, AWD, Fuel efficient, Navigation, Turbo, V8, V6, Trunk space, Smooth ride, Leather etc.) AWD, fuel efficient, smooth quiet ride, tech features<\/p>\n\n<p>Desired transmission (auto\/manual, etc): Auto<\/p>\n\n<p>Intended use: (Daily Driver, Family Car, Weekend Car, Track Toy, Project Car, Work Truck, Off roading etc.) daily driver to downtown Chicago ~80 miles roundtrip<\/p>\n\n<p>Vehicles you&#39;ve already considered: XC60, X3, Lincoln Corsair<\/p>\n\n<p>Is this your 1st vehicle: No<\/p>\n\n<p>Do you need a Warranty: Yes<\/p>\n\n<p>Can you do Minor work on your own vehicle: (fluids, alternator, battery, brake pads etc) No<\/p>\n\n<p>Can you do Major work on your own vehicle: (engine and transmission, timing belt\/chains, body work, suspension etc ) No<\/p>\n\n<p>Additional Notes: 2013 X3 w\/ 97k miles has transfer case issue and needs tires + brakes. Considering a fluid change or disabling transfer case but more and more considering new car if makes sense. Starting to travel more so need to decide soon. Do I attempt to keep X3 going or bite the bullet and go for something new? Looking for something similar to x3 for my needs.<\/p>\n<\/div>","71":"<div class=\"md\"><p><strong>Location:<\/strong> New York, NY but will be driving it mostly in Worcester, MA<\/p>\n\n<p><strong>Price:<\/strong> Ideally around $8k<\/p>\n\n<p><strong>Lease or Buy:<\/strong> Buy<\/p>\n\n<p><strong>New or Used:<\/strong> Used<\/p>\n\n<p><strong>Type of Vehicle:<\/strong> Honestly any type, but preferably a truck or SUV<\/p>\n\n<p><strong>Must-Haves:<\/strong> Reliable, AWD<\/p>\n\n<p><strong>Desired transmission:<\/strong> Auto<\/p>\n\n<p><strong>Intended Use:<\/strong> Daily driver<\/p>\n\n<p><strong>Vehicles you&#39;ve already considered:<\/strong> Toyota Land Cruiser, Chevy Colorado\/GMC Canyon, Toyota Tundra, Toyota Tacoma, Ford F-150<\/p>\n\n<p><strong>Is this your 1st vehicle:<\/strong> Yes<\/p>\n\n<p><strong>Do you need a warranty:<\/strong> No, which is why I need a reliable car<\/p>\n\n<p><strong>Can you do minor work:<\/strong> Yes, to an extent<\/p>\n\n<p><strong>Can you do major work:<\/strong> No<\/p>\n<\/div>","72":"<div class=\"md\"><p>Location: Florida, United States<\/p>\n\n<p>Price range: 15k to 25k<\/p>\n\n<p>Lease or Buy: Buy<\/p>\n\n<p>New or used: Either<\/p>\n\n<p>Type of vehicle: Sedan or hatchback or coupe.  <\/p>\n\n<p>Must haves: I would like it to be kind of quick and it has to be a five seater.<\/p>\n\n<p>Desired transmission (auto\/manual, etc): Auto  <\/p>\n\n<p>Intended use: Daily<\/p>\n\n<p>Vehicles you&#39;ve already considered: VW GTI, Honda Accord sport 2.0t  <\/p>\n\n<p>Is this your 1st vehicle: No<\/p>\n\n<p>Do you need a Warranty: No<\/p>\n\n<p>Can you do Minor work on your own vehicle: Yes<\/p>\n\n<p>Can you do Major work on your own vehicle: Some<\/p>\n<\/div>","73":"<div class=\"md\"><p>Location: Ohio<\/p>\n\n<p>Price Range: Around $20k<\/p>\n\n<p>Lease or Buy: Buy<\/p>\n\n<p>New or Used: Used <\/p>\n\n<p>Type of Vehicle: Car<\/p>\n\n<p>Must Haves: Leather, Adaptive Cruise, High End Sound System (Bose, Harmon\/Kardon, Lexicon, Bowers &amp; Wilkins, etc). CarPlay would be nice.<\/p>\n\n<p>Desired Transmission: Automatic <\/p>\n\n<p>Intended Use: Daily Driver<\/p>\n\n<p>Vehicles I\u2019ve Considered: 2018-2020 Buick Regal Sportback, 2019 Honda Insight, 2017-2019 Ford Fusion Sport, 2016-2019 Cadillac ATS &amp; CTS, 2014-2016 Mercedes E Class<\/p>\n\n<p>Warranty: maybe<\/p>\n\n<p>Minor Work: no<\/p>\n\n<p>Major Work: no<\/p>\n\n<p>Additional Notes: I can either trade in my current car, a 2013 Honda CRV that I love, to get one of these, or I could keep my CRV and find something cheaper. I want a car for the improved driving dynamics and style. However if I keep my CRV and get a cheaper 2nd car, I wouldn\u2019t be able to get the features I am looking for.<\/p>\n<\/div>","74":"<div class=\"md\"><p>From a dealer in North Carolina. Been offered a 2009 equinox for 6.5k otd 100k miles. This includes a 800 Doc fee and then another 150 in other fees. Car looks to be in OK condition. Any thoughts as to if this is a decent deal?<\/p>\n<\/div>","75":"<div class=\"md\"><p>[gel\u00f6scht]<\/p>\n<\/div>","76":"<div class=\"md\"><p>I&#39;m looking at getting a new car this year, I&#39;m heavily leaning to an SUV, but open to a sedan, I have it narrowed down to:<\/p>\n\n<p>2021 Ford Escape<\/p>\n\n<p>2021 Nissan Rogue (the all new one)<\/p>\n\n<p>2022 Hyundai Tuscon (the all new one)<\/p>\n\n<p>and for the sedan, I like the new Hyundai Sonata <\/p>\n\n<h1><\/h1>\n\n<p>I really like the all-digital speedometer on them (I would add the Bronco to the list, but that&#39;s not all digital).  I don&#39;t think too many other cars out there have it - except maybe for VW.  I like cars too, and find Honda&#39;s and Toyota&#39;s pretty boring.  <\/p>\n\n<p>I understand that with all the options I want, all would be close to $40,000.  I would want AWD on my car, leather seats, and the all-digital speedometer.  <\/p>\n\n<p>My current car is a 2012 Ford Focus - which I like, but with 122k miles, it&#39;s probably time to move on and upgrade.  I also live in NJ, and this would be my only car.  I&#39;m not overly concerned about maintenance either - I can do some small stuff myself, but since it&#39;s a new car, maintenance won&#39;t come into play for several years (I&#39;ve had almost no issues with my Focus, and nothing major - aside from normal maintenance, I think I&#39;ve put under $1000 into it on problems).<\/p>\n\n<p><strong>So, let me know what you think: the Escape, Rogue, Tucson, or Sonata.<\/strong><\/p>\n<\/div>","77":"<div class=\"md\"><p>Ford Mustang 2004-1995<\/p>\n<\/div>","78":"<div class=\"md\"><p>Should I go for the mk3 supra or the Porsche 944? I love the style of both cars, but I&#39;m looking for something reliable as a daily.<\/p>\n<\/div>","79":"<div class=\"md\"><p>Does\/Did anyone own a Lexus LS 500? How do you like it so far? I am hearing mixed feedback from other forums on the engine performance.<\/p>\n<\/div>","80":"<div class=\"md\"><p>[entfernt]<\/p>\n<\/div>","81":"<div class=\"md\"><p>Location: Northeastern PA.<\/p>\n\n<p>Price range: Max of $35,000-$40,000.<\/p>\n\n<p>Lease or Buy: Buy<\/p>\n\n<p>New or used: New<\/p>\n\n<p>Type of vehicle: SUV \/ Crossover. Don&#39;t need a third row.<\/p>\n\n<p>Must haves: AWD, Wireless CarPlay, Remote start via phone app, panoramic sun\/moonroof, great warranty, bonus for a solid amount of HP.<\/p>\n\n<p>Desired transmission (auto\/manual, etc): Torque converter auto, CVTs and dual clutches would be considered, but they have so many negatives for a DD that I hope to have for the next 10 years.<\/p>\n\n<p>Intended use: Daily Driver<\/p>\n\n<p>Vehicles you&#39;ve already considered: Hyundai Tucson, Hyundai Santa Fe, Mazda CX-5, Kia Sorento, Honda CRV, Toyota RAV4.<\/p>\n\n<p>Is this your 1st vehicle: No, but it will be my only vehicle.<\/p>\n\n<p>Do you need a Warranty: Yes, would like as long a warranty as possible.<\/p>\n\n<p>Can you do Minor work on your own vehicle: No.<\/p>\n\n<p>Can you do Major work on your own vehicle: No.<\/p>\n\n<p>Additional Notes: I normally lease sport sedans (have a Kia Stinger right now) but the pandemic really opened my eyes as to how little I drive anymore, and it&#39;s not likely to rebound much after COVID ends. I don&#39;t want to get a total snoozefest of a SUV\/CUV, but I know I&#39;m going to be stepping down in the fun department. I would like that step down to not be a huge leap down if possible.<\/p>\n\n<p>It seems like every car I&#39;m looking at has a flaw, maybe I need to rethink what I am looking for or my price range.<\/p>\n\n<p>The upcoming Tuscon N Line is currently top of my list, but there are rumors going both ways about it either getting an upgraded engine or if it&#39;ll keep the standard engine.<\/p>\n\n<p>New Kia Sorento is very attractive, but the top engine trim has a DCT. Even though it&#39;s a new Wet DCT, still unsure about it&#39;s longevity.<\/p>\n\n<p>Mazda CX-5, Beautiful, decent engine options, great predicted reliability, but no wireless CarPlay or panoramic sun\/moonroof.<\/p>\n\n<p>Honda CRV = CVT, no wireless carplay, and no panoramic moonroof.<\/p>\n\n<p>What SUVs have I overlooked?<\/p>\n<\/div>","82":"<div class=\"md\"><p>Location: Ontario Canada<\/p>\n\n<p>Price range: &lt;45k<\/p>\n\n<p>Lease or Buy: Either <\/p>\n\n<p>New or used: used<\/p>\n\n<p>Type of vehicle: Fun car\/Daily<\/p>\n\n<p>Must haves: Fun driving dynamics, enough space for a couple sets of golf clubs, android auto, Some luxuries. I&#39;m ok with a coupe <\/p>\n\n<p>Desired transmission (auto\/manual, etc): either works. Best bet would be auto with paddles <\/p>\n\n<p>Intended use: Will double as a daily driver and a fun car. So needs to be somewhat practical. But only somewhat. Hoping to take it out for fun around some twisties but also to and from work and such<\/p>\n\n<p>Vehicles you&#39;ve already considered: 440i, s3 mustang gt, wrx, golf r, KIA stinger <\/p>\n\n<p>Is this your 1st vehicle: No<\/p>\n\n<p>Do you need a Warranty: No but always good to have<\/p>\n\n<p>Can you do Minor work on your own vehicle: Only very minor work<\/p>\n\n<p>Can you do Major work on your own vehicle: No<\/p>\n\n<p>Additional Notes: looking for something fun to zip around in that can also double as my ride to and from work and errands. Tech is nice, so nothing too dated. Needs to have android auto. Safety features are a bonus like adaptive cruise\/blind spot monitoring etc.<\/p>\n<\/div>","83":"<div class=\"md\"><blockquote>\n<p><strong>Location:<\/strong> Ontario<br\/>\n<strong>Price range:<\/strong> 35k<br\/>\n<strong>Lease or Buy: Not sure which is better<\/strong><br\/>\n<strong>New or used:<\/strong> Thinking New<br\/>\n<strong>Type of vehicle:<\/strong> Sedan<br\/>\n<strong>Must haves:<\/strong> Latest Safety Features<br\/>\n<strong>Desired transmission (auto\/manual, etc): Auto<\/strong><br\/>\n<strong>Intended use:<\/strong> Daily Driver From Markham to Toroto<br\/>\n<strong>Vehicles you&#39;ve already considered:<\/strong> Honda Civic Hatchback or Toyota Corolla<br\/>\n<strong>Is this your 1st vehicle:<\/strong> Yes<br\/>\n<strong>Do you need a Warranty:<\/strong> Not sure<br\/>\n<strong>Can you do Minor work on your own vehicle:<\/strong> Yes<br\/>\n<strong>Can you do Major work on your own vehicle:<\/strong> No<br\/>\n<strong>Additional Notes:<\/strong><\/p>\n<\/blockquote>\n\n<ul>\n<li>I am looking for a good comfortable ride back and forth from work\n\n<ul>\n<li>So good safety features (In side Toronto driving makes me nervous)<\/li>\n<li>Good sound system its about a 40-60 min drive 1 way<\/li>\n<\/ul><\/li>\n<li>Will probably buy around Sept. <\/li>\n<li>I wrote Honda Civic Hatchback 2021 because of the number of reviews I have been watching online. But would love to know what other options I should look at. \n\n<ul>\n<li>I like the roomyness of the car but some of the tech features of the Toyota Corolla where nicer from the video reviews.<\/li>\n<li>This is was the review that really was great told me about the 2020 models<br\/>\n\n<ul>\n<li><a href=\"https:\/\/youtu.be\/I_1FPzRtLMA\">https:\/\/youtu.be\/I_1FPzRtLMA<\/a><\/li>\n<li>Also is it worth getting the 2020 or 2021?<\/li>\n<\/ul><\/li>\n<\/ul><\/li>\n<\/ul>\n<\/div>","84":"<div class=\"md\"><p>Anything wrong with a white car?<\/p>\n\n<p>I want to buy an White used car. I&#39;m a mid 20s guy. Someone told me white cars are for women, and now I can&#39;t get it out of my head!<\/p>\n<\/div>","85":"<div class=\"md\"><p>What are the odds Toyota makes a manual supra this year?<\/p>\n<\/div>","86":"<div class=\"md\"><p>Any help would be appreciated!<\/p>\n\n<p>Location: West Coast<\/p>\n\n<p>Price range: 30,000-60,000<\/p>\n\n<p>Lease or Buy: buy<\/p>\n\n<p>New or used: new or lightly used, 3 yrs old max<\/p>\n\n<p>Type of vehicle: sporty\/luxury four door sedan<\/p>\n\n<p>Must haves: smooth ride, ventilated seats, window curtains, luxurious, reliable, roomy, unique, <\/p>\n\n<p>Desired transmission: auto<\/p>\n\n<p>Intended use: daily Driver<\/p>\n\n<p>Vehicles you&#39;ve already considered: 2018-2020 Genesis G80 3.3 sport, Lexus GS, Chevy SS, Kia stinger, Genesis G70, Kia K900<\/p>\n\n<p>Is this your 1st vehicle:no<\/p>\n\n<p>Do you need a Warranty: yes<\/p>\n\n<p>Can you do Minor work on your own vehicle: only very basic things like changing lightbulbs, engine air filter, wipers.<\/p>\n\n<p>Can you do Major work on your own vehicle: No.<\/p>\n\n<p>Additional Notes: reliability and uniqueness are paramount for me, not so much price.<\/p>\n\n<p>I&#39;d want a car like the Lexus GS but more unique and without the weird track pad. The G80 is really at the top of my list but ideally it&#39;d be lighter and more fuel efficient, and sportier.<\/p>\n\n<p>Kia stinger could work but not enough space inside<\/p>\n<\/div>","87":"<div class=\"md\"><p><strong>Location:<\/strong> New Jersey<\/p>\n\n<p><strong>Price range:<\/strong> $25,000-$30,000<\/p>\n\n<p><strong>Lease or Buy:<\/strong> Both<\/p>\n\n<p><strong>New or used:<\/strong> Both (or used with low miles)<\/p>\n\n<p><strong>Type of vehicle:<\/strong> Coupe, Sedan, SUV, Hatchback, Wagon, Pickup<\/p>\n\n<p><strong>Must haves:<\/strong> RWD or AWD, nice looks, fairly sizeable aftermarket (so no econoboxes). If it&#39;s a Sedan\/Coupe, V8 is an absolute must.<\/p>\n\n<p><strong>Desired transmission (auto\/manual, etc):<\/strong> Preferably auto<\/p>\n\n<p><strong>Intended use:<\/strong> Daily driver and weekend warrior<\/p>\n\n<p><strong>Vehicles you&#39;ve already considered:<\/strong> Jeep Renegade, Ford Bronco Sport, Dodge Challenger RT, Ford Mustang GT, Mercedes-Benz C63 AMG (W204), 2021 Mazda3 Hatchback 2.5T<\/p>\n\n<p><strong>Is this your 1st vehicle:<\/strong> No<\/p>\n\n<p><strong>Do you need a Warranty:<\/strong> No<\/p>\n\n<p><strong>Can you do Minor work on your own vehicle:<\/strong> Yes<\/p>\n\n<p><strong>Can you do Major work on your own vehicle:<\/strong> No, I have no time.<\/p>\n\n<p><strong>Additional Notes:<\/strong> I&#39;m a young guy. I need a young guy car. I have a pretty great job coming up so cost really isn&#39;t too much of a concern, hence why I considered the C63 in the first place. It has everything I need but I can&#39;t seem to score one at a reasonable price. I&#39;ve driven my Taurus for six years now.<\/p>\n<\/div>","88":"<div class=\"md\"><p>[gel\u00f6scht]<\/p>\n<\/div>","89":"<div class=\"md\"><p>Ferrari Cali spider 1957<\/p>\n<\/div>","90":"<div class=\"md\"><p>2021 Corvette C8<\/p>\n<\/div>","91":"<div class=\"md\"><p>I got a jeep Cherokee suv but really want to trade it.<\/p>\n<\/div>","92":"<div class=\"md\"><p>Passport<\/p>\n<\/div>","93":"<div class=\"md\"><p>&gt;Do you want a 2 door or 4 door?<\/p>\n\n<p>Both are fine. <\/p>\n\n<p>I can&#39;t do a mustang because of the snow and hills. If it wasn&#39;t for that I would have jumped on board. The WRX STI is still in consideration. I have to schedule a test drive with a dealership. I&#39;m gonna be tracking it for these two years. I want to but I can wait on that until I get the supra.<\/p>\n<\/div>"},"comment_toplevel":{"0":1,"1":1,"2":1,"3":1,"4":1,"5":1,"6":1,"7":1,"8":1,"9":1,"10":1,"11":1,"12":1,"13":1,"14":1,"15":1,"16":1,"17":1,"18":1,"19":1,"20":1,"21":1,"22":1,"23":1,"24":1,"25":1,"26":1,"27":1,"28":1,"29":1,"30":1,"31":1,"32":1,"33":1,"34":1,"35":1,"36":1,"37":1,"38":1,"39":1,"40":1,"41":1,"42":1,"43":1,"44":1,"45":1,"46":1,"47":1,"48":1,"49":1,"50":1,"51":1,"52":1,"53":1,"54":1,"55":1,"56":1,"57":1,"58":1,"59":1,"60":1,"61":1,"62":1,"63":1,"64":1,"65":1,"66":1,"67":1,"68":1,"69":1,"70":1,"71":1,"72":1,"73":1,"74":1,"75":1,"76":1,"77":1,"78":1,"79":1,"80":1,"81":1,"82":1,"83":1,"84":1,"85":1,"86":1,"87":1,"88":1,"89":1,"90":1,"91":1,"92":1,"93":1},"comment_distinguished":{"0":null,"1":null,"2":null,"3":null,"4":null,"5":null,"6":null,"7":null,"8":null,"9":null,"10":null,"11":null,"12":null,"13":null,"14":null,"15":null,"16":null,"17":null,"18":null,"19":null,"20":null,"21":null,"22":null,"23":null,"24":null,"25":null,"26":null,"27":null,"28":null,"29":null,"30":null,"31":null,"32":null,"33":null,"34":null,"35":null,"36":null,"37":null,"38":null,"39":null,"40":null,"41":null,"42":null,"43":null,"44":null,"45":null,"46":null,"47":null,"48":null,"49":null,"50":null,"51":null,"52":null,"53":null,"54":null,"55":null,"56":null,"57":null,"58":null,"59":null,"60":null,"61":null,"62":null,"63":null,"64":null,"65":null,"66":null,"67":null,"68":null,"69":null,"70":null,"71":null,"72":null,"73":null,"74":null,"75":null,"76":null,"77":null,"78":null,"79":null,"80":null,"81":null,"82":null,"83":null,"84":null,"85":null,"86":null,"87":null,"88":null,"89":null,"90":null,"91":null,"92":null,"93":null},"comment_edited":{"0":false,"1":false,"2":false,"3":false,"4":false,"5":1611842272.0,"6":false,"7":false,"8":1611876931.0,"9":false,"10":false,"11":false,"12":false,"13":false,"14":false,"15":false,"16":false,"17":false,"18":1611717860.0,"19":false,"20":false,"21":false,"22":false,"23":false,"24":false,"25":false,"26":false,"27":false,"28":false,"29":false,"30":false,"31":false,"32":false,"33":false,"34":1612466519.0,"35":false,"36":false,"37":1612131078.0,"38":false,"39":false,"40":false,"41":false,"42":false,"43":false,"44":false,"45":false,"46":false,"47":false,"48":false,"49":false,"50":false,"51":false,"52":1611733132.0,"53":false,"54":false,"55":false,"56":false,"57":false,"58":false,"59":false,"60":false,"61":false,"62":false,"63":false,"64":false,"65":false,"66":false,"67":false,"68":false,"69":false,"70":1612034624.0,"71":1612055155.0,"72":false,"73":false,"74":false,"75":false,"76":false,"77":false,"78":false,"79":false,"80":false,"81":false,"82":false,"83":false,"84":false,"85":false,"86":1614265620.0,"87":false,"88":false,"89":false,"90":false,"91":false,"92":false,"93":false},"comment_is_submitter":{"0":false,"1":false,"2":false,"3":false,"4":false,"5":false,"6":false,"7":false,"8":false,"9":false,"10":false,"11":false,"12":false,"13":false,"14":false,"15":false,"16":false,"17":false,"18":false,"19":false,"20":false,"21":false,"22":false,"23":false,"24":false,"25":false,"26":false,"27":false,"28":false,"29":false,"30":false,"31":false,"32":false,"33":false,"34":false,"35":false,"36":false,"37":false,"38":false,"39":false,"40":false,"41":false,"42":false,"43":false,"44":false,"45":false,"46":false,"47":false,"48":false,"49":false,"50":false,"51":false,"52":false,"53":false,"54":false,"55":false,"56":false,"57":false,"58":false,"59":false,"60":false,"61":false,"62":false,"63":false,"64":false,"65":false,"66":false,"67":false,"68":false,"69":false,"70":false,"71":false,"72":false,"73":false,"74":false,"75":false,"76":false,"77":false,"78":false,"79":false,"80":false,"81":false,"82":false,"83":false,"84":false,"85":false,"86":false,"87":false,"88":false,"89":false,"90":false,"91":false,"92":false,"93":false},"comment_score":{"0":7,"1":5,"2":3,"3":3,"4":3,"5":3,"6":3,"7":3,"8":3,"9":3,"10":3,"11":2,"12":2,"13":2,"14":2,"15":2,"16":2,"17":2,"18":2,"19":2,"20":2,"21":2,"22":2,"23":2,"24":2,"25":2,"26":2,"27":2,"28":2,"29":2,"30":2,"31":2,"32":2,"33":2,"34":2,"35":2,"36":2,"37":2,"38":1,"39":1,"40":1,"41":1,"42":1,"43":1,"44":1,"45":1,"46":1,"47":1,"48":1,"49":1,"50":1,"51":1,"52":1,"53":1,"54":1,"55":1,"56":1,"57":1,"58":1,"59":1,"60":1,"61":1,"62":1,"63":1,"64":1,"65":1,"66":1,"67":1,"68":1,"69":1,"70":1,"71":1,"72":1,"73":1,"74":1,"75":1,"76":1,"77":1,"78":1,"79":1,"80":1,"81":1,"82":1,"83":1,"84":1,"85":1,"86":1,"87":0,"88":0,"89":0,"90":-2,"91":-1,"92":-1,"93":1},"comment_stickied":{"0":false,"1":false,"2":false,"3":false,"4":false,"5":false,"6":false,"7":false,"8":false,"9":false,"10":false,"11":false,"12":false,"13":false,"14":false,"15":false,"16":false,"17":false,"18":false,"19":false,"20":false,"21":false,"22":false,"23":false,"24":false,"25":false,"26":false,"27":false,"28":false,"29":false,"30":false,"31":false,"32":false,"33":false,"34":false,"35":false,"36":false,"37":false,"38":false,"39":false,"40":false,"41":false,"42":false,"43":false,"44":false,"45":false,"46":false,"47":false,"48":false,"49":false,"50":false,"51":false,"52":false,"53":false,"54":false,"55":false,"56":false,"57":false,"58":false,"59":false,"60":false,"61":false,"62":false,"63":false,"64":false,"65":false,"66":false,"67":false,"68":false,"69":false,"70":false,"71":false,"72":false,"73":false,"74":false,"75":false,"76":false,"77":false,"78":false,"79":false,"80":false,"81":false,"82":false,"83":false,"84":false,"85":false,"86":false,"87":false,"88":false,"89":false,"90":false,"91":false,"92":false,"93":false},"author_id":{"0":"","1":"","2":"gw5zf","3":"edoecfq","4":"6gma8v3e","5":"905mpupe","6":"3y969","7":"2emj4tv9","8":"3e4zrxgt","9":"1t7d8asp","10":"5jts91g7","11":"","12":"8nlwzu81","13":"8mz846tm","14":"1ey1ro3v","15":"","16":"","17":"5c5e8aoz","18":"a3e4d","19":"2efqfxno","20":"8jq0mm1o","21":"eiul4","22":"466wdq6j","23":"5l1t6","24":"3gh6v2kb","25":"a1dvr6tq","26":"j8lks","27":"89c4lm7k","28":"qbbal","29":"ovdb6","30":"9m56k3yd","31":"10tu02","32":"3dbxu94s","33":"v87dd","34":"88tea2vh","35":"ovdb6","36":"6cci20l","37":"63fipl0s","38":"8s0xy7ik","39":"","40":"155oyi","41":"","42":"1je8uu81","43":"5nacfkp6","44":"6ha5a","45":"7ahbwugi","46":"2sjsh99x","47":"a05e0x27","48":"7j0gt5l1","49":"","50":"4dep1g1g","51":"3olkdea7","52":"","53":"","54":"jf122oo","55":"4iq9xd81","56":"5wabw","57":"6och3n1s","58":"5he50mgu","59":"","60":"3wfssv9v","61":"7rgow526","62":"7rgow526","63":"rr2a4xy","64":"4p2q40rg","65":"","66":"4p2q40rg","67":"e0tza","68":"","69":"4me44","70":"zxr4w","71":"4jjn35pw","72":"e5nxqad","73":"49sghill","74":"krj0f","75":"","76":"3si8e29f","77":"","78":"66mxgn29","79":"a2h3fp7l","80":"","81":"4hbde","82":"","83":"9l9djp91","84":"ovdb6","85":"gw5zf","86":"","87":"","88":"","89":"a3x6ypw3","90":"9d1j50fi","91":"8qx89pqx","92":"12yu4i","93":"89c4lm7k"},"author_name":{"0":"","1":"","2":"SpaceGhost1992","3":"wildoolittle","4":"Ginkahygamy","5":"Maxwell945","6":"OutsideObserver","7":"countingolaf","8":"rhyyz","9":"indianapail32","10":"lloydpalace","11":"","12":"NET-24","13":"throwaway878348","14":"asdfoneplusone","15":"drdisrespecting00","16":"","17":"hockeyplayer2244","18":"timpdx","19":"itrawrz","20":"Optimal-Hyena-1492","21":"DrunkenChekhov","22":"YogiOnPath","23":"pooramericanboy","24":"rainbow1905","25":"tossernineteen84","26":"ArnoTheFox","27":"Deep-Ad3797","28":"Shhhhhhhh_Im_At_Work","29":"arsenalastronaut","30":"Mrstockboy","31":"cdcyclist","32":"bustedrollermouse","33":"ss3jcb448","34":"waterpenwall","35":"arsenalastronaut","36":"WorkAccount_NoNSFW","37":"Nomadic_asset","38":"ShreyashStonieCrusts","39":"","40":"coreysimulator","41":"farahhhhh","42":"UiteNume","43":"ibringulove","44":"M3tatron","45":"Scary_Contribution_5","46":"_theZincSaucier_","47":"Uiopso","48":"Anubis_XV","49":"","50":"rkadiego","51":"chi-bacon-bits","52":"","53":"","54":"familydude213","55":"Abuudiii","56":"jonnygc8","57":"watchreviewblog","58":"theblackestballoons","59":"","60":"Buck_Buckminster","61":"gollyyyy","62":"gollyyyy","63":"Master_Zaheer","64":"Txuejd7u","65":"","66":"Txuejd7u","67":"bluebaloo525","68":"","69":"Citi19","70":"jbudzo","71":"LessDougDeMuro","72":"JaredK742","73":"jake199911","74":"tommywommywom","75":"","76":"cydonia8388","77":"","78":"I_have_BigSad","79":"Violet0704","80":"","81":"DaytonaZ33","82":"mrteeth5","83":"nogoodhunter2","84":"arsenalastronaut","85":"SpaceGhost1992","86":"","87":"ScarletHighlander","88":"","89":"blackDrag0nxx123","90":"No_Farm_2035","91":"Charming_Passenger_8","92":"HoraceGrand","93":"Deep-Ad3797"}}